{"flowContents":{"identifier":"88c21c99-eba0-3bb8-800f-cba645bb9cb7","instanceIdentifier":"48c4ba6e-d338-32aa-ba8f-640cbd9fa6f4","name":"CEF Log Parsing","comments":"","position":{"x":446.9999860853543,"y":296.9999942181852},"processGroups":[],"remoteProcessGroups":[],"processors":[{"identifier":"fa610e3a-cfda-3a64-a3d5-943f0ae42338","instanceIdentifier":"990d9023-ce1f-32cf-9434-0026ca43c7db","name":"PutHive3Streaming","comments":"","position":{"x":752.0,"y":1824.0},"type":"org.apache.nifi.processors.hive.PutHive3Streaming","bundle":{"group":"org.apache.nifi","artifact":"nifi-hive3-nar","version":"1.23.1.2.1.6.0-323"},"properties":{"hive3-stream-call-timeout":"0","kerberos-principal":null,"rollback-on-failure":"false","hive3-stream-metastore-uri":"thrift://cdp.3.144.230.228.nip.io:9083","hive3-stream-records-per-transaction":"0","kerberos-credentials-service":null,"hive3-stream-part-vals":null,"hive3-config-resources":"/etc/hive/conf.cloudera.hive/hive-site.xml","hive3-stream-table-name":"cef_events_orc_v2","record-reader":"2224fa09-7305-3d59-838d-a39f264238aa","hive3-stream-transactions-per-batch":"1","hive3-stream-database-name":"default","hive3-stream-disable-optimizations":"false"},"propertyDescriptors":{"hive3-stream-call-timeout":{"name":"hive3-stream-call-timeout","displayName":"Call Timeout","identifiesControllerService":false,"sensitive":false},"kerberos-password":{"name":"kerberos-password","displayName":"Kerberos Password","identifiesControllerService":false,"sensitive":true},"kerberos-principal":{"name":"kerberos-principal","displayName":"Kerberos Principal","identifiesControllerService":false,"sensitive":false},"rollback-on-failure":{"name":"rollback-on-failure","displayName":"Rollback On Failure","identifiesControllerService":false,"sensitive":false},"hive3-stream-metastore-uri":{"name":"hive3-stream-metastore-uri","displayName":"Hive Metastore URI","identifiesControllerService":false,"sensitive":false},"hive3-stream-records-per-transaction":{"name":"hive3-stream-records-per-transaction","displayName":"Records per Transaction","identifiesControllerService":false,"sensitive":false},"kerberos-credentials-service":{"name":"kerberos-credentials-service","displayName":"Kerberos Credentials Service","identifiesControllerService":true,"sensitive":false},"hive3-stream-part-vals":{"name":"hive3-stream-part-vals","displayName":"Static Partition Values","identifiesControllerService":false,"sensitive":false},"hive3-config-resources":{"name":"hive3-config-resources","displayName":"Hive Configuration Resources","identifiesControllerService":false,"sensitive":false,"resourceDefinition":{"cardinality":"MULTIPLE","resourceTypes":["FILE"]}},"hive3-stream-table-name":{"name":"hive3-stream-table-name","displayName":"Table Name","identifiesControllerService":false,"sensitive":false},"record-reader":{"name":"record-reader","displayName":"Record Reader","identifiesControllerService":true,"sensitive":false},"hive3-stream-transactions-per-batch":{"name":"hive3-stream-transactions-per-batch","displayName":"Transactions per Batch","identifiesControllerService":false,"sensitive":false},"hive3-stream-database-name":{"name":"hive3-stream-database-name","displayName":"Database Name","identifiesControllerService":false,"sensitive":false},"hive3-stream-disable-optimizations":{"name":"hive3-stream-disable-optimizations","displayName":"Disable Streaming Optimizations","identifiesControllerService":false,"sensitive":false}},"style":{},"schedulingPeriod":"0 sec","schedulingStrategy":"TIMER_DRIVEN","executionNode":"ALL","penaltyDuration":"30 sec","yieldDuration":"1 sec","bulletinLevel":"WARN","runDurationMillis":0,"concurrentlySchedulableTaskCount":1,"autoTerminatedRelationships":["success","failure"],"scheduledState":"ENABLED","retryCount":0,"retriedRelationships":[],"backoffMechanism":"PENALIZE_FLOWFILE","maxBackoffPeriod":"10 mins","componentType":"PROCESSOR","groupIdentifier":"88c21c99-eba0-3bb8-800f-cba645bb9cb7"},{"identifier":"a2c8d1dd-8f03-3af7-a745-621b04cb33a8","instanceIdentifier":"01459cc0-e594-3da6-98cd-384a8997b0d3","name":"Lookup Geo","comments":"","position":{"x":256.0,"y":1272.0},"type":"org.apache.nifi.processors.standard.LookupRecord","bundle":{"group":"org.apache.nifi","artifact":"nifi-standard-nar","version":"1.23.1.2.1.6.0-323"},"properties":{"result-contents":"record-fields","routing-strategy":"route-to-success","record-path-lookup-miss-result-cache-size":"0","result-record-path":"/","record-writer":"dd72ffcb-a5af-3204-937a-7616b9c3b7d1","latitude":"toString(/latitude,\"UTF-8\")","record-reader":"2224fa09-7305-3d59-838d-a39f264238aa","lookup-service":"6d8d4783-336d-319d-b2ce-11b8462f0bbb","record-update-strategy":"use-property","key":"toString(/extension_cs4, \"UTF-8\")","longitude":"toString(/longitude,\"UTF-8\")"},"propertyDescriptors":{"result-contents":{"name":"result-contents","displayName":"Record Result Contents","identifiesControllerService":false,"sensitive":false},"routing-strategy":{"name":"routing-strategy","displayName":"Routing Strategy","identifiesControllerService":false,"sensitive":false},"record-path-lookup-miss-result-cache-size":{"name":"record-path-lookup-miss-result-cache-size","displayName":"Cache Size","identifiesControllerService":false,"sensitive":false},"result-record-path":{"name":"result-record-path","displayName":"Result RecordPath","identifiesControllerService":false,"sensitive":false},"record-writer":{"name":"record-writer","displayName":"Record Writer","identifiesControllerService":true,"sensitive":false},"latitude":{"name":"latitude","displayName":"latitude","identifiesControllerService":false,"sensitive":false},"record-reader":{"name":"record-reader","displayName":"Record Reader","identifiesControllerService":true,"sensitive":false},"lookup-service":{"name":"lookup-service","displayName":"Lookup Service","identifiesControllerService":true,"sensitive":false},"record-update-strategy":{"name":"record-update-strategy","displayName":"Record Update Strategy","identifiesControllerService":false,"sensitive":false},"key":{"name":"key","displayName":"key","identifiesControllerService":false,"sensitive":false},"longitude":{"name":"longitude","displayName":"longitude","identifiesControllerService":false,"sensitive":false}},"style":{},"schedulingPeriod":"0 sec","schedulingStrategy":"TIMER_DRIVEN","executionNode":"ALL","penaltyDuration":"30 sec","yieldDuration":"1 sec","bulletinLevel":"WARN","runDurationMillis":0,"concurrentlySchedulableTaskCount":1,"autoTerminatedRelationships":[],"scheduledState":"ENABLED","retryCount":0,"retriedRelationships":[],"backoffMechanism":"PENALIZE_FLOWFILE","maxBackoffPeriod":"10 mins","componentType":"PROCESSOR","groupIdentifier":"88c21c99-eba0-3bb8-800f-cba645bb9cb7"},{"identifier":"36fcc2dd-6e55-3970-9c63-03c5b6663ec4","instanceIdentifier":"25b33c8e-f942-3979-8f2f-a4b5b8e88803","name":"Subscribe to Kafka CEF Logs","comments":"","position":{"x":256.0,"y":-64.0},"type":"org.apache.nifi.processors.kafka.pubsub.ConsumeKafka_2_6","bundle":{"group":"org.apache.nifi","artifact":"nifi-kafka-2-6-nar","version":"1.23.1.2.1.6.0-323"},"properties":{"header-name-regex":null,"Commit Offsets":"true","group.id":"NiFi Group","bootstrap.servers":"edge2ai-1.dim.local:9092","topic_type":"names","sasl.kerberos.principal":null,"sasl.kerberos.service.name":null,"kerberos-credentials-service":null,"max-uncommit-offset-wait":"1 secs","sasl.mechanism":"GSSAPI","honor-transactions":"true","kerberos-user-service":null,"message-header-encoding":"UTF-8","message-demarcator":null,"client.id":"nifi-consumer","sasl.username":null,"max.poll.records":"10000","aws.profile.name":null,"security.protocol":"PLAINTEXT","ssl.context.service":null,"sasl.token.auth":"false","sasl.kerberos.keytab":null,"Communications Timeout":"60 secs","topic":"cef","separate-by-key":"false","key-attribute-encoding":"utf-8","auto.offset.reset":"latest"},"propertyDescriptors":{"header-name-regex":{"name":"header-name-regex","displayName":"Headers to Add as Attributes (Regex)","identifiesControllerService":false,"sensitive":false},"Commit Offsets":{"name":"Commit Offsets","displayName":"Commit Offsets","identifiesControllerService":false,"sensitive":false},"group.id":{"name":"group.id","displayName":"Group ID","identifiesControllerService":false,"sensitive":false},"bootstrap.servers":{"name":"bootstrap.servers","displayName":"Kafka Brokers","identifiesControllerService":false,"sensitive":false},"topic_type":{"name":"topic_type","displayName":"Topic Name Format","identifiesControllerService":false,"sensitive":false},"sasl.kerberos.principal":{"name":"sasl.kerberos.principal","displayName":"Kerberos Principal","identifiesControllerService":false,"sensitive":false},"sasl.kerberos.service.name":{"name":"sasl.kerberos.service.name","displayName":"Kerberos Service Name","identifiesControllerService":false,"sensitive":false},"kerberos-credentials-service":{"name":"kerberos-credentials-service","displayName":"Kerberos Credentials Service","identifiesControllerService":true,"sensitive":false},"max-uncommit-offset-wait":{"name":"max-uncommit-offset-wait","displayName":"Max Uncommitted Time","identifiesControllerService":false,"sensitive":false},"sasl.mechanism":{"name":"sasl.mechanism","displayName":"SASL Mechanism","identifiesControllerService":false,"sensitive":false},"honor-transactions":{"name":"honor-transactions","displayName":"Honor Transactions","identifiesControllerService":false,"sensitive":false},"kerberos-user-service":{"name":"kerberos-user-service","displayName":"Kerberos User Service","identifiesControllerService":true,"sensitive":false},"message-header-encoding":{"name":"message-header-encoding","displayName":"Message Header Encoding","identifiesControllerService":false,"sensitive":false},"message-demarcator":{"name":"message-demarcator","displayName":"Message Demarcator","identifiesControllerService":false,"sensitive":false},"client.id":{"name":"client.id","displayName":"client.id","identifiesControllerService":false,"sensitive":false},"sasl.username":{"name":"sasl.username","displayName":"Username","identifiesControllerService":false,"sensitive":false},"max.poll.records":{"name":"max.poll.records","displayName":"Max Poll Records","identifiesControllerService":false,"sensitive":false},"aws.profile.name":{"name":"aws.profile.name","displayName":"AWS Profile Name","identifiesControllerService":false,"sensitive":false},"security.protocol":{"name":"security.protocol","displayName":"Security Protocol","identifiesControllerService":false,"sensitive":false},"ssl.context.service":{"name":"ssl.context.service","displayName":"SSL Context Service","identifiesControllerService":true,"sensitive":false},"sasl.token.auth":{"name":"sasl.token.auth","displayName":"Token Authentication","identifiesControllerService":false,"sensitive":false},"sasl.kerberos.keytab":{"name":"sasl.kerberos.keytab","displayName":"Kerberos Keytab","identifiesControllerService":false,"sensitive":false,"resourceDefinition":{"cardinality":"SINGLE","resourceTypes":["FILE"]}},"Communications Timeout":{"name":"Communications Timeout","displayName":"Communications Timeout","identifiesControllerService":false,"sensitive":false},"topic":{"name":"topic","displayName":"Topic Name(s)","identifiesControllerService":false,"sensitive":false},"separate-by-key":{"name":"separate-by-key","displayName":"Separate By Key","identifiesControllerService":false,"sensitive":false},"sasl.password":{"name":"sasl.password","displayName":"Password","identifiesControllerService":false,"sensitive":true},"key-attribute-encoding":{"name":"key-attribute-encoding","displayName":"Key Attribute Encoding","identifiesControllerService":false,"sensitive":false},"auto.offset.reset":{"name":"auto.offset.reset","displayName":"Offset Reset","identifiesControllerService":false,"sensitive":false}},"style":{},"schedulingPeriod":"0 sec","schedulingStrategy":"TIMER_DRIVEN","executionNode":"ALL","penaltyDuration":"30 sec","yieldDuration":"1 sec","bulletinLevel":"WARN","runDurationMillis":0,"concurrentlySchedulableTaskCount":1,"autoTerminatedRelationships":[],"scheduledState":"ENABLED","retryCount":0,"retriedRelationships":[],"backoffMechanism":"PENALIZE_FLOWFILE","maxBackoffPeriod":"10 mins","componentType":"PROCESSOR","groupIdentifier":"88c21c99-eba0-3bb8-800f-cba645bb9cb7"},{"identifier":"89292f75-832f-3e9b-8892-e19374175803","instanceIdentifier":"46d14641-dccf-3e84-8012-dc6574026209","name":"Transforms","comments":"","position":{"x":256.0,"y":1080.0},"type":"org.apache.nifi.processors.standard.UpdateRecord","bundle":{"group":"org.apache.nifi","artifact":"nifi-standard-nar","version":"1.23.1.2.1.6.0-323"},"properties":{"//tsepoch":"${field.value:toNumber():format(\"yyyy-MM-dd'T'HH:mm:ss.SSS'Z'\",\"ET\")}","//extension_shost":"${field.value:append('.net.com')}","//ts_day":"${field.value:toNumber():format(\"dd\",\"ET\")}","//extension_ahost":"${field.value:append('.net.com')}","//ts_part":"${field.value:toNumber():format(\"yyyyMMdd\",\"ET\")}","record-writer":"dd72ffcb-a5af-3204-937a-7616b9c3b7d1","//ts_hour":"${field.value:toNumber():format(\"HH\",\"ET\")}","record-reader":"2c3df069-092b-3565-853f-d40814c9564a","replacement-value-strategy":"literal-value","//extension_dvchost":"${field.value:append('.net.com')}"},"propertyDescriptors":{"//tsepoch":{"name":"//tsepoch","displayName":"//tsepoch","identifiesControllerService":false,"sensitive":false},"//extension_shost":{"name":"//extension_shost","displayName":"//extension_shost","identifiesControllerService":false,"sensitive":false},"//ts_day":{"name":"//ts_day","displayName":"//ts_day","identifiesControllerService":false,"sensitive":false},"//extension_ahost":{"name":"//extension_ahost","displayName":"//extension_ahost","identifiesControllerService":false,"sensitive":false},"//ts_part":{"name":"//ts_part","displayName":"//ts_part","identifiesControllerService":false,"sensitive":false},"record-writer":{"name":"record-writer","displayName":"Record Writer","identifiesControllerService":true,"sensitive":false},"//ts_hour":{"name":"//ts_hour","displayName":"//ts_hour","identifiesControllerService":false,"sensitive":false},"record-reader":{"name":"record-reader","displayName":"Record Reader","identifiesControllerService":true,"sensitive":false},"replacement-value-strategy":{"name":"replacement-value-strategy","displayName":"Replacement Value Strategy","identifiesControllerService":false,"sensitive":false},"//extension_dvchost":{"name":"//extension_dvchost","displayName":"//extension_dvchost","identifiesControllerService":false,"sensitive":false}},"style":{},"schedulingPeriod":"0 sec","schedulingStrategy":"TIMER_DRIVEN","executionNode":"ALL","penaltyDuration":"30 sec","yieldDuration":"1 sec","bulletinLevel":"WARN","runDurationMillis":0,"concurrentlySchedulableTaskCount":1,"autoTerminatedRelationships":[],"scheduledState":"ENABLED","retryCount":0,"retriedRelationships":[],"backoffMechanism":"PENALIZE_FLOWFILE","maxBackoffPeriod":"10 mins","componentType":"PROCESSOR","groupIdentifier":"88c21c99-eba0-3bb8-800f-cba645bb9cb7"},{"identifier":"2b613617-9897-3023-8778-add667fb99e6","instanceIdentifier":"883a05d6-e964-3149-8284-d504932eefb1","name":"Re-route Time Errors","comments":"","position":{"x":256.0,"y":1448.0},"type":"org.apache.nifi.processors.standard.RouteOnAttribute","bundle":{"group":"org.apache.nifi","artifact":"nifi-standard-nar","version":"1.23.1.2.1.6.0-323"},"properties":{"Routing Strategy":"Route to Property name","time.exception":"${cef.tsepoch:gt(${now():toNumber()})}"},"propertyDescriptors":{"Routing Strategy":{"name":"Routing Strategy","displayName":"Routing Strategy","identifiesControllerService":false,"sensitive":false},"time.exception":{"name":"time.exception","displayName":"time.exception","identifiesControllerService":false,"sensitive":false}},"style":{},"schedulingPeriod":"0 sec","schedulingStrategy":"TIMER_DRIVEN","executionNode":"ALL","penaltyDuration":"30 sec","yieldDuration":"1 sec","bulletinLevel":"WARN","runDurationMillis":0,"concurrentlySchedulableTaskCount":1,"autoTerminatedRelationships":[],"scheduledState":"ENABLED","retryCount":0,"retriedRelationships":[],"backoffMechanism":"PENALIZE_FLOWFILE","maxBackoffPeriod":"10 mins","componentType":"PROCESSOR","groupIdentifier":"88c21c99-eba0-3bb8-800f-cba645bb9cb7"},{"identifier":"5981c418-68ab-37ed-b996-c163955afcea","instanceIdentifier":"66ff78a4-7320-3dc3-a59f-8c19c0abe017","name":"Subscribe to MQTT","comments":"","position":{"x":728.0,"y":256.0},"type":"org.apache.nifi.processors.mqtt.ConsumeMQTT","bundle":{"group":"org.apache.nifi","artifact":"nifi-mqtt-nar","version":"1.23.1.2.1.6.0-323"},"properties":{"Max Queue Size":"60","Client ID":"cef-simulator","Last Will QoS Level":"0","Connection Timeout (seconds)":"30","record-writer":null,"Broker URI":"tcp://edge2ai-1.dim.local:1883","add-attributes-as-fields":"true","SSL Context Service":null,"Username":null,"Session state":"true","Session Expiry Interval":"24 hrs","Quality of Service(QoS)":"0","Last Will Message":null,"Last Will Topic":null,"Topic Filter":"cef/#","record-reader":null,"Group ID":null,"message-demarcator":null,"MQTT Specification Version":"0","Keep Alive Interval (seconds)":"60","Last Will Retain":"false"},"propertyDescriptors":{"Max Queue Size":{"name":"Max Queue Size","displayName":"Max Queue Size","identifiesControllerService":false,"sensitive":false},"Client ID":{"name":"Client ID","displayName":"Client ID","identifiesControllerService":false,"sensitive":false},"Last Will QoS Level":{"name":"Last Will QoS Level","displayName":"Last Will QoS Level","identifiesControllerService":false,"sensitive":false},"Connection Timeout (seconds)":{"name":"Connection Timeout (seconds)","displayName":"Connection Timeout (seconds)","identifiesControllerService":false,"sensitive":false},"record-writer":{"name":"record-writer","displayName":"Record Writer","identifiesControllerService":true,"sensitive":false},"Broker URI":{"name":"Broker URI","displayName":"Broker URI","identifiesControllerService":false,"sensitive":false},"add-attributes-as-fields":{"name":"add-attributes-as-fields","displayName":"Add attributes as fields","identifiesControllerService":false,"sensitive":false},"SSL Context Service":{"name":"SSL Context Service","displayName":"SSL Context Service","identifiesControllerService":true,"sensitive":false},"Username":{"name":"Username","displayName":"Username","identifiesControllerService":false,"sensitive":false},"Session state":{"name":"Session state","displayName":"Session state","identifiesControllerService":false,"sensitive":false},"Session Expiry Interval":{"name":"Session Expiry Interval","displayName":"Session Expiry Interval","identifiesControllerService":false,"sensitive":false},"Quality of Service(QoS)":{"name":"Quality of Service(QoS)","displayName":"Quality of Service (QoS)","identifiesControllerService":false,"sensitive":false},"Last Will Message":{"name":"Last Will Message","displayName":"Last Will Message","identifiesControllerService":false,"sensitive":false},"Last Will Topic":{"name":"Last Will Topic","displayName":"Last Will Topic","identifiesControllerService":false,"sensitive":false},"Topic Filter":{"name":"Topic Filter","displayName":"Topic Filter","identifiesControllerService":false,"sensitive":false},"record-reader":{"name":"record-reader","displayName":"Record Reader","identifiesControllerService":true,"sensitive":false},"Group ID":{"name":"Group ID","displayName":"Group ID","identifiesControllerService":false,"sensitive":false},"message-demarcator":{"name":"message-demarcator","displayName":"Message Demarcator","identifiesControllerService":false,"sensitive":false},"MQTT Specification Version":{"name":"MQTT Specification Version","displayName":"MQTT Specification Version","identifiesControllerService":false,"sensitive":false},"Keep Alive Interval (seconds)":{"name":"Keep Alive Interval (seconds)","displayName":"Keep Alive Interval (seconds)","identifiesControllerService":false,"sensitive":false},"Password":{"name":"Password","displayName":"Password","identifiesControllerService":false,"sensitive":true},"Last Will Retain":{"name":"Last Will Retain","displayName":"Last Will Retain","identifiesControllerService":false,"sensitive":false}},"style":{},"schedulingPeriod":"0 sec","schedulingStrategy":"TIMER_DRIVEN","executionNode":"ALL","penaltyDuration":"30 sec","yieldDuration":"1 sec","bulletinLevel":"WARN","runDurationMillis":0,"concurrentlySchedulableTaskCount":1,"autoTerminatedRelationships":["parse.failure"],"scheduledState":"ENABLED","retryCount":0,"retriedRelationships":[],"backoffMechanism":"PENALIZE_FLOWFILE","maxBackoffPeriod":"10 mins","componentType":"PROCESSOR","groupIdentifier":"88c21c99-eba0-3bb8-800f-cba645bb9cb7"},{"identifier":"43710b2a-0a9d-36c6-b62f-7d8e89c0786a","instanceIdentifier":"2fa47dbd-f6f2-3bbe-80aa-74f501b2050a","name":"RegEx Capture CEF-Ambiguous Values ","comments":"","position":{"x":256.0,"y":312.0},"type":"org.apache.nifi.processors.standard.ExtractText","bundle":{"group":"org.apache.nifi","artifact":"nifi-standard-nar","version":"1.23.1.2.1.6.0-323"},"properties":{"Enable Unicode Predefined Character Classes":"false","Permit Whitespace and Comments in Pattern":"false","cef.eventmsg":"(?<=eventmsg=)(.*)(?= deviceSeverity)","Enable Unicode-aware Case Folding":"false","Enable DOTALL Mode":"false","Enable Unix Lines Mode":"false","extract-text-enable-named-groups":"false","cef.device.severity":"(?<=deviceSeverity=)(.*)(?=tsepoch)","Maximum Buffer Size":"1 MB","Enable Canonical Equivalence":"false","Enable Case-insensitive Matching":"false","Enable Multiline Mode":"false","cef.eventid":"(?<=eventId=)(.*)(?= eventmsg)","Maximum Capture Group Length":"1024","cef.tsepoch":"(?<=tsepoch=)(.*)(?=   cs3=)","Enable Literal Parsing of the Pattern":"false","Character Set":"UTF-8","Include Capture Group 0":"false","extract-text-enable-repeating-capture-group":"false"},"propertyDescriptors":{"Enable Unicode Predefined Character Classes":{"name":"Enable Unicode Predefined Character Classes","displayName":"Enable Unicode Predefined Character Classes","identifiesControllerService":false,"sensitive":false},"Permit Whitespace and Comments in Pattern":{"name":"Permit Whitespace and Comments in Pattern","displayName":"Permit Whitespace and Comments in Pattern","identifiesControllerService":false,"sensitive":false},"cef.eventmsg":{"name":"cef.eventmsg","displayName":"cef.eventmsg","identifiesControllerService":false,"sensitive":false},"Enable Unicode-aware Case Folding":{"name":"Enable Unicode-aware Case Folding","displayName":"Enable Unicode-aware Case Folding","identifiesControllerService":false,"sensitive":false},"Enable DOTALL Mode":{"name":"Enable DOTALL Mode","displayName":"Enable DOTALL Mode","identifiesControllerService":false,"sensitive":false},"Enable Unix Lines Mode":{"name":"Enable Unix Lines Mode","displayName":"Enable Unix Lines Mode","identifiesControllerService":false,"sensitive":false},"extract-text-enable-named-groups":{"name":"extract-text-enable-named-groups","displayName":"Enable named group support","identifiesControllerService":false,"sensitive":false},"cef.device.severity":{"name":"cef.device.severity","displayName":"cef.device.severity","identifiesControllerService":false,"sensitive":false},"Maximum Buffer Size":{"name":"Maximum Buffer Size","displayName":"Maximum Buffer Size","identifiesControllerService":false,"sensitive":false},"Enable Canonical Equivalence":{"name":"Enable Canonical Equivalence","displayName":"Enable Canonical Equivalence","identifiesControllerService":false,"sensitive":false},"Enable Case-insensitive Matching":{"name":"Enable Case-insensitive Matching","displayName":"Enable Case-insensitive Matching","identifiesControllerService":false,"sensitive":false},"Enable Multiline Mode":{"name":"Enable Multiline Mode","displayName":"Enable Multiline Mode","identifiesControllerService":false,"sensitive":false},"cef.eventid":{"name":"cef.eventid","displayName":"cef.eventid","identifiesControllerService":false,"sensitive":false},"Maximum Capture Group Length":{"name":"Maximum Capture Group Length","displayName":"Maximum Capture Group Length","identifiesControllerService":false,"sensitive":false},"cef.tsepoch":{"name":"cef.tsepoch","displayName":"cef.tsepoch","identifiesControllerService":false,"sensitive":false},"Enable Literal Parsing of the Pattern":{"name":"Enable Literal Parsing of the Pattern","displayName":"Enable Literal Parsing of the Pattern","identifiesControllerService":false,"sensitive":false},"Character Set":{"name":"Character Set","displayName":"Character Set","identifiesControllerService":false,"sensitive":false},"Include Capture Group 0":{"name":"Include Capture Group 0","displayName":"Include Capture Group 0","identifiesControllerService":false,"sensitive":false},"extract-text-enable-repeating-capture-group":{"name":"extract-text-enable-repeating-capture-group","displayName":"Enable repeating capture group","identifiesControllerService":false,"sensitive":false}},"style":{},"schedulingPeriod":"0 sec","schedulingStrategy":"TIMER_DRIVEN","executionNode":"ALL","penaltyDuration":"30 sec","yieldDuration":"1 sec","bulletinLevel":"WARN","runDurationMillis":0,"concurrentlySchedulableTaskCount":1,"autoTerminatedRelationships":[],"scheduledState":"ENABLED","retryCount":0,"retriedRelationships":[],"backoffMechanism":"PENALIZE_FLOWFILE","maxBackoffPeriod":"10 mins","componentType":"PROCESSOR","groupIdentifier":"88c21c99-eba0-3bb8-800f-cba645bb9cb7"},{"identifier":"ad33cf8f-626b-324c-a459-6b0f8380eebf","instanceIdentifier":"c714889c-5716-3c90-9a4d-db2c62fad4f0","name":"PutHDFS","comments":"","position":{"x":-216.0,"y":-40.0},"type":"org.apache.nifi.processors.hadoop.PutHDFS","bundle":{"group":"org.apache.nifi","artifact":"nifi-hadoop-nar","version":"1.23.1.2.1.6.0-323"},"properties":{"Permissions umask":null,"Hadoop Configuration Resources":"/etc/hive/conf.cloudera.hive/hive-site.xml,/etc/hive/conf.cloudera.hive/core-site.xml,/etc/hive/conf.cloudera.hive/hdfs-site.xml","Remote Owner":null,"Additional Classpath Resources":null,"Compression codec":"NONE","IO Buffer Size":null,"Remote Group":null,"Block Size":null,"kerberos-credentials-service":null,"Kerberos Keytab":null,"Ignore Locality":"false","Kerberos Principal":null,"Replication":null,"kerberos-user-service":null,"writing-strategy":"writeAndRename","Kerberos Relogin Period":"4 hours","Directory":"/user/admin/cef_archive","Conflict Resolution Strategy":"fail"},"propertyDescriptors":{"Permissions umask":{"name":"Permissions umask","displayName":"Permissions umask","identifiesControllerService":false,"sensitive":false},"Hadoop Configuration Resources":{"name":"Hadoop Configuration Resources","displayName":"Hadoop Configuration Resources","identifiesControllerService":false,"sensitive":false,"resourceDefinition":{"cardinality":"MULTIPLE","resourceTypes":["FILE"]}},"Remote Owner":{"name":"Remote Owner","displayName":"Remote Owner","identifiesControllerService":false,"sensitive":false},"Additional Classpath Resources":{"name":"Additional Classpath Resources","displayName":"Additional Classpath Resources","identifiesControllerService":false,"sensitive":false,"resourceDefinition":{"cardinality":"MULTIPLE","resourceTypes":["FILE","DIRECTORY"]}},"Compression codec":{"name":"Compression codec","displayName":"Compression codec","identifiesControllerService":false,"sensitive":false},"IO Buffer Size":{"name":"IO Buffer Size","displayName":"IO Buffer Size","identifiesControllerService":false,"sensitive":false},"Remote Group":{"name":"Remote Group","displayName":"Remote Group","identifiesControllerService":false,"sensitive":false},"Block Size":{"name":"Block Size","displayName":"Block Size","identifiesControllerService":false,"sensitive":false},"kerberos-credentials-service":{"name":"kerberos-credentials-service","displayName":"Kerberos Credentials Service","identifiesControllerService":true,"sensitive":false},"Kerberos Password":{"name":"Kerberos Password","displayName":"Kerberos Password","identifiesControllerService":false,"sensitive":true},"Kerberos Keytab":{"name":"Kerberos Keytab","displayName":"Kerberos Keytab","identifiesControllerService":false,"sensitive":false,"resourceDefinition":{"cardinality":"SINGLE","resourceTypes":["FILE"]}},"Ignore Locality":{"name":"Ignore Locality","displayName":"Ignore Locality","identifiesControllerService":false,"sensitive":false},"Kerberos Principal":{"name":"Kerberos Principal","displayName":"Kerberos Principal","identifiesControllerService":false,"sensitive":false},"Replication":{"name":"Replication","displayName":"Replication","identifiesControllerService":false,"sensitive":false},"kerberos-user-service":{"name":"kerberos-user-service","displayName":"Kerberos User Service","identifiesControllerService":true,"sensitive":false},"writing-strategy":{"name":"writing-strategy","displayName":"Writing Strategy","identifiesControllerService":false,"sensitive":false},"Kerberos Relogin Period":{"name":"Kerberos Relogin Period","displayName":"Kerberos Relogin Period","identifiesControllerService":false,"sensitive":false},"Directory":{"name":"Directory","displayName":"Directory","identifiesControllerService":false,"sensitive":false},"Conflict Resolution Strategy":{"name":"Conflict Resolution Strategy","displayName":"Conflict Resolution Strategy","identifiesControllerService":false,"sensitive":false}},"style":{},"schedulingPeriod":"0 sec","schedulingStrategy":"TIMER_DRIVEN","executionNode":"ALL","penaltyDuration":"30 sec","yieldDuration":"1 sec","bulletinLevel":"WARN","runDurationMillis":0,"concurrentlySchedulableTaskCount":1,"autoTerminatedRelationships":["success","failure"],"scheduledState":"ENABLED","retryCount":0,"retriedRelationships":[],"backoffMechanism":"PENALIZE_FLOWFILE","maxBackoffPeriod":"10 mins","componentType":"PROCESSOR","groupIdentifier":"88c21c99-eba0-3bb8-800f-cba645bb9cb7"},{"identifier":"4e6d6623-b49d-3e0e-9b5b-f0e20150c594","instanceIdentifier":"f1c9e653-9c56-3626-96e3-625baaac4422","name":"ReplaceText","comments":"","position":{"x":256.0,"y":136.0},"type":"org.apache.nifi.processors.standard.ReplaceText","bundle":{"group":"org.apache.nifi","artifact":"nifi-standard-nar","version":"1.23.1.2.1.6.0-323"},"properties":{"Regular Expression":"\\n","Replacement Value":" ","Evaluation Mode":"Line-by-Line","Text to Prepend":null,"Line-by-Line Evaluation Mode":"All","Character Set":"UTF-8","Maximum Buffer Size":"1 MB","Replacement Strategy":"Literal Replace","Text to Append":null},"propertyDescriptors":{"Regular Expression":{"name":"Regular Expression","displayName":"Search Value","identifiesControllerService":false,"sensitive":false},"Replacement Value":{"name":"Replacement Value","displayName":"Replacement Value","identifiesControllerService":false,"sensitive":false},"Evaluation Mode":{"name":"Evaluation Mode","displayName":"Evaluation Mode","identifiesControllerService":false,"sensitive":false},"Text to Prepend":{"name":"Text to Prepend","displayName":"Text to Prepend","identifiesControllerService":false,"sensitive":false},"Line-by-Line Evaluation Mode":{"name":"Line-by-Line Evaluation Mode","displayName":"Line-by-Line Evaluation Mode","identifiesControllerService":false,"sensitive":false},"Character Set":{"name":"Character Set","displayName":"Character Set","identifiesControllerService":false,"sensitive":false},"Maximum Buffer Size":{"name":"Maximum Buffer Size","displayName":"Maximum Buffer Size","identifiesControllerService":false,"sensitive":false},"Replacement Strategy":{"name":"Replacement Strategy","displayName":"Replacement Strategy","identifiesControllerService":false,"sensitive":false},"Text to Append":{"name":"Text to Append","displayName":"Text to Append","identifiesControllerService":false,"sensitive":false}},"style":{},"schedulingPeriod":"0 sec","schedulingStrategy":"TIMER_DRIVEN","executionNode":"ALL","penaltyDuration":"30 sec","yieldDuration":"1 sec","bulletinLevel":"WARN","runDurationMillis":0,"concurrentlySchedulableTaskCount":1,"autoTerminatedRelationships":["failure"],"scheduledState":"ENABLED","retryCount":0,"retriedRelationships":[],"backoffMechanism":"PENALIZE_FLOWFILE","maxBackoffPeriod":"10 mins","componentType":"PROCESSOR","groupIdentifier":"88c21c99-eba0-3bb8-800f-cba645bb9cb7"},{"identifier":"87942329-60c4-3157-a9ea-6b10f9adf400","instanceIdentifier":"ebeaf220-0023-3308-9b00-f6009980d521","name":"Generate CEF Logs to MQTT","comments":"","position":{"x":728.0,"y":8.0},"type":"org.apache.nifi.processors.standard.ExecuteProcess","bundle":{"group":"org.apache.nifi","artifact":"nifi-standard-nar","version":"1.23.1.2.1.6.0-323"},"properties":{"Command":"python3","Redirect Error Stream":"false","Working Directory":null,"Argument Delimiter":" ","Batch Duration":null,"Command Arguments":"/opt/demo/cef-simulate-mqtt.py"},"propertyDescriptors":{"Command":{"name":"Command","displayName":"Command","identifiesControllerService":false,"sensitive":false},"Redirect Error Stream":{"name":"Redirect Error Stream","displayName":"Redirect Error Stream","identifiesControllerService":false,"sensitive":false},"Working Directory":{"name":"Working Directory","displayName":"Working Directory","identifiesControllerService":false,"sensitive":false},"Argument Delimiter":{"name":"Argument Delimiter","displayName":"Argument Delimiter","identifiesControllerService":false,"sensitive":false},"Batch Duration":{"name":"Batch Duration","displayName":"Batch Duration","identifiesControllerService":false,"sensitive":false},"Command Arguments":{"name":"Command Arguments","displayName":"Command Arguments","identifiesControllerService":false,"sensitive":false}},"style":{},"schedulingPeriod":"1 sec","schedulingStrategy":"TIMER_DRIVEN","executionNode":"ALL","penaltyDuration":"30 sec","yieldDuration":"1 sec","bulletinLevel":"WARN","runDurationMillis":0,"concurrentlySchedulableTaskCount":1,"autoTerminatedRelationships":["success"],"scheduledState":"ENABLED","retryCount":0,"retriedRelationships":[],"backoffMechanism":"PENALIZE_FLOWFILE","maxBackoffPeriod":"10 mins","componentType":"PROCESSOR","groupIdentifier":"88c21c99-eba0-3bb8-800f-cba645bb9cb7"},{"identifier":"f18e1d79-c52f-3635-9305-16ff4f1b2815","instanceIdentifier":"1f9ccd80-84ba-3fa3-8efb-f2572a767f00","name":"JoltTransformJSON","comments":"","position":{"x":256.0,"y":704.0},"type":"org.apache.nifi.processors.standard.JoltTransformJSON","bundle":{"group":"org.apache.nifi","artifact":"nifi-standard-nar","version":"1.23.1.2.1.6.0-323"},"properties":{"jolt-spec":"[\n  {\n    \"operation\": \"shift\",\n    \"spec\": {\n      \"header\": {\n        \"*\": \"&1_&\"\n      },\n      \"extension\": {\n        \"*\": \"&1_&\"\n      },\n      \"_raw\": \"raw\"\n    }\n  },\n  {\n    \"operation\": \"default\",\n    \"spec\": {\n      \"device_severity\": \"${cef.device.severity}\",\n      \"eventid\": \"${cef.eventid}\",\n      \"eventmsg\": \"${cef.eventmsg}\",\n      \"tsepoch\": \"${cef.tsepoch}\",\n      \"raw\": \"raw\",\n\t  \"latitude\": 0.00,\n\t  \"longitude\": 0.00,\n\t  \"ts_day\": \"${cef.tsepoch}\",\n\t  \"ts_hour\": \"${cef.tsepoch}\",\n\t  \"ts_part\": \"${cef.tsepoch}\"\n    }\n  },\n  {\n    \"operation\": \"modify-overwrite-beta\",\n    \"spec\": {\n      \"*\": \"=trim\"\n    }\n  },\n  {\n    \"operation\": \"modify-overwrite-beta\",\n    \"spec\": {\n      \"*\": \"=toLower\"\n    }\n  },\n  {\n    \"operation\": \"modify-overwrite-beta\",\n    \"spec\": {\n      \"severity\": \"=concat(@(1,header_severity),'-',@(1,device_severity))\"\n    }\n  }\n  ]","jolt-transform":"jolt-transform-chain","jolt-custom-class":null,"jolt-custom-modules":null,"pretty_print":"false","Transform Cache Size":"1"},"propertyDescriptors":{"jolt-spec":{"name":"jolt-spec","displayName":"Jolt Specification","identifiesControllerService":false,"sensitive":false,"resourceDefinition":{"cardinality":"SINGLE","resourceTypes":["FILE","TEXT"]}},"jolt-transform":{"name":"jolt-transform","displayName":"Jolt Transformation DSL","identifiesControllerService":false,"sensitive":false},"jolt-custom-class":{"name":"jolt-custom-class","displayName":"Custom Transformation Class Name","identifiesControllerService":false,"sensitive":false},"jolt-custom-modules":{"name":"jolt-custom-modules","displayName":"Custom Module Directory","identifiesControllerService":false,"sensitive":false,"resourceDefinition":{"cardinality":"MULTIPLE","resourceTypes":["FILE","DIRECTORY"]}},"pretty_print":{"name":"pretty_print","displayName":"Pretty Print","identifiesControllerService":false,"sensitive":false},"Transform Cache Size":{"name":"Transform Cache Size","displayName":"Transform Cache Size","identifiesControllerService":false,"sensitive":false}},"style":{},"schedulingPeriod":"0 sec","schedulingStrategy":"TIMER_DRIVEN","executionNode":"ALL","penaltyDuration":"30 sec","yieldDuration":"1 sec","bulletinLevel":"WARN","runDurationMillis":0,"concurrentlySchedulableTaskCount":1,"autoTerminatedRelationships":[],"scheduledState":"ENABLED","retryCount":0,"retriedRelationships":[],"backoffMechanism":"PENALIZE_FLOWFILE","maxBackoffPeriod":"10 mins","componentType":"PROCESSOR","groupIdentifier":"88c21c99-eba0-3bb8-800f-cba645bb9cb7"},{"identifier":"82151105-1bef-3692-84b0-fa173ae82c31","instanceIdentifier":"6fe5ba4d-c0df-30ab-9ad0-f4b2d950fe2c","name":"Publish Device Logs to Kafka","comments":"","position":{"x":728.0,"y":464.0},"type":"org.apache.nifi.processors.kafka.pubsub.PublishKafka_2_6","bundle":{"group":"org.apache.nifi","artifact":"nifi-kafka-2-6-nar","version":"1.23.1.2.1.6.0-323"},"properties":{"compression.type":"none","attribute-name-regex":null,"bootstrap.servers":"edge2ai-1.dim.local:9092","sasl.kerberos.principal":null,"sasl.kerberos.service.name":null,"kerberos-credentials-service":null,"kafka-key":null,"partition":null,"sasl.mechanism":"GSSAPI","max.block.ms":"5 sec","message-header-encoding":"UTF-8","kerberos-user-service":null,"message-demarcator":null,"transactional-id-prefix":null,"client.id":"nifi-cef-producer","ack.wait.time":"5 secs","sasl.username":null,"use-transactions":"false","acks":"0","aws.profile.name":null,"security.protocol":"PLAINTEXT","ssl.context.service":null,"max.request.size":"1 MB","sasl.token.auth":"false","Failure Strategy":"Route to Failure","partitioner.class":"org.apache.kafka.clients.producer.internals.DefaultPartitioner","sasl.kerberos.keytab":null,"topic":"cef","key-attribute-encoding":"utf-8"},"propertyDescriptors":{"compression.type":{"name":"compression.type","displayName":"Compression Type","identifiesControllerService":false,"sensitive":false},"attribute-name-regex":{"name":"attribute-name-regex","displayName":"Attributes to Send as Headers (Regex)","identifiesControllerService":false,"sensitive":false},"bootstrap.servers":{"name":"bootstrap.servers","displayName":"Kafka Brokers","identifiesControllerService":false,"sensitive":false},"sasl.kerberos.principal":{"name":"sasl.kerberos.principal","displayName":"Kerberos Principal","identifiesControllerService":false,"sensitive":false},"sasl.kerberos.service.name":{"name":"sasl.kerberos.service.name","displayName":"Kerberos Service Name","identifiesControllerService":false,"sensitive":false},"kerberos-credentials-service":{"name":"kerberos-credentials-service","displayName":"Kerberos Credentials Service","identifiesControllerService":true,"sensitive":false},"kafka-key":{"name":"kafka-key","displayName":"Kafka Key","identifiesControllerService":false,"sensitive":false},"partition":{"name":"partition","displayName":"Partition","identifiesControllerService":false,"sensitive":false},"sasl.mechanism":{"name":"sasl.mechanism","displayName":"SASL Mechanism","identifiesControllerService":false,"sensitive":false},"max.block.ms":{"name":"max.block.ms","displayName":"Max Metadata Wait Time","identifiesControllerService":false,"sensitive":false},"message-header-encoding":{"name":"message-header-encoding","displayName":"Message Header Encoding","identifiesControllerService":false,"sensitive":false},"kerberos-user-service":{"name":"kerberos-user-service","displayName":"Kerberos User Service","identifiesControllerService":true,"sensitive":false},"message-demarcator":{"name":"message-demarcator","displayName":"Message Demarcator","identifiesControllerService":false,"sensitive":false},"transactional-id-prefix":{"name":"transactional-id-prefix","displayName":"Transactional Id Prefix","identifiesControllerService":false,"sensitive":false},"client.id":{"name":"client.id","displayName":"client.id","identifiesControllerService":false,"sensitive":false},"ack.wait.time":{"name":"ack.wait.time","displayName":"Acknowledgment Wait Time","identifiesControllerService":false,"sensitive":false},"sasl.username":{"name":"sasl.username","displayName":"Username","identifiesControllerService":false,"sensitive":false},"use-transactions":{"name":"use-transactions","displayName":"Use Transactions","identifiesControllerService":false,"sensitive":false},"acks":{"name":"acks","displayName":"Delivery Guarantee","identifiesControllerService":false,"sensitive":false},"aws.profile.name":{"name":"aws.profile.name","displayName":"AWS Profile Name","identifiesControllerService":false,"sensitive":false},"security.protocol":{"name":"security.protocol","displayName":"Security Protocol","identifiesControllerService":false,"sensitive":false},"ssl.context.service":{"name":"ssl.context.service","displayName":"SSL Context Service","identifiesControllerService":true,"sensitive":false},"max.request.size":{"name":"max.request.size","displayName":"Max Request Size","identifiesControllerService":false,"sensitive":false},"sasl.token.auth":{"name":"sasl.token.auth","displayName":"Token Authentication","identifiesControllerService":false,"sensitive":false},"Failure Strategy":{"name":"Failure Strategy","displayName":"Failure Strategy","identifiesControllerService":false,"sensitive":false},"partitioner.class":{"name":"partitioner.class","displayName":"Partitioner class","identifiesControllerService":false,"sensitive":false},"sasl.kerberos.keytab":{"name":"sasl.kerberos.keytab","displayName":"Kerberos Keytab","identifiesControllerService":false,"sensitive":false,"resourceDefinition":{"cardinality":"SINGLE","resourceTypes":["FILE"]}},"topic":{"name":"topic","displayName":"Topic Name","identifiesControllerService":false,"sensitive":false},"sasl.password":{"name":"sasl.password","displayName":"Password","identifiesControllerService":false,"sensitive":true},"key-attribute-encoding":{"name":"key-attribute-encoding","displayName":"Key Attribute Encoding","identifiesControllerService":false,"sensitive":false}},"style":{},"schedulingPeriod":"0 sec","schedulingStrategy":"TIMER_DRIVEN","executionNode":"ALL","penaltyDuration":"30 sec","yieldDuration":"1 sec","bulletinLevel":"WARN","runDurationMillis":0,"concurrentlySchedulableTaskCount":1,"autoTerminatedRelationships":["success","failure"],"scheduledState":"ENABLED","retryCount":0,"retriedRelationships":[],"backoffMechanism":"PENALIZE_FLOWFILE","maxBackoffPeriod":"10 mins","componentType":"PROCESSOR","groupIdentifier":"88c21c99-eba0-3bb8-800f-cba645bb9cb7"},{"identifier":"c82a21f9-eb14-3435-99d5-0eb34d08abf3","instanceIdentifier":"c6a18fd6-afb7-3b8a-935f-c0c793c2b27a","name":"PutHDFS","comments":"","position":{"x":256.0,"y":1840.0},"type":"org.apache.nifi.processors.hadoop.PutHDFS","bundle":{"group":"org.apache.nifi","artifact":"nifi-hadoop-nar","version":"1.23.1.2.1.6.0-323"},"properties":{"Permissions umask":null,"Hadoop Configuration Resources":"/etc/hive/conf.cloudera.hive/hive-site.xml,/etc/hive/conf.cloudera.hive/core-site.xml,/etc/hive/conf.cloudera.hive/hdfs-site.xml","Remote Owner":null,"Additional Classpath Resources":null,"Compression codec":"NONE","IO Buffer Size":null,"Remote Group":null,"Block Size":null,"kerberos-credentials-service":null,"Kerberos Keytab":null,"Ignore Locality":"false","Kerberos Principal":null,"Replication":null,"kerberos-user-service":null,"writing-strategy":"writeAndRename","Kerberos Relogin Period":"4 hours","Directory":"/warehouse/tablespace/external/hive/cef_events","Conflict Resolution Strategy":"replace"},"propertyDescriptors":{"Permissions umask":{"name":"Permissions umask","displayName":"Permissions umask","identifiesControllerService":false,"sensitive":false},"Hadoop Configuration Resources":{"name":"Hadoop Configuration Resources","displayName":"Hadoop Configuration Resources","identifiesControllerService":false,"sensitive":false,"resourceDefinition":{"cardinality":"MULTIPLE","resourceTypes":["FILE"]}},"Remote Owner":{"name":"Remote Owner","displayName":"Remote Owner","identifiesControllerService":false,"sensitive":false},"Additional Classpath Resources":{"name":"Additional Classpath Resources","displayName":"Additional Classpath Resources","identifiesControllerService":false,"sensitive":false,"resourceDefinition":{"cardinality":"MULTIPLE","resourceTypes":["FILE","DIRECTORY"]}},"Compression codec":{"name":"Compression codec","displayName":"Compression codec","identifiesControllerService":false,"sensitive":false},"IO Buffer Size":{"name":"IO Buffer Size","displayName":"IO Buffer Size","identifiesControllerService":false,"sensitive":false},"Remote Group":{"name":"Remote Group","displayName":"Remote Group","identifiesControllerService":false,"sensitive":false},"Block Size":{"name":"Block Size","displayName":"Block Size","identifiesControllerService":false,"sensitive":false},"kerberos-credentials-service":{"name":"kerberos-credentials-service","displayName":"Kerberos Credentials Service","identifiesControllerService":true,"sensitive":false},"Kerberos Password":{"name":"Kerberos Password","displayName":"Kerberos Password","identifiesControllerService":false,"sensitive":true},"Kerberos Keytab":{"name":"Kerberos Keytab","displayName":"Kerberos Keytab","identifiesControllerService":false,"sensitive":false,"resourceDefinition":{"cardinality":"SINGLE","resourceTypes":["FILE"]}},"Ignore Locality":{"name":"Ignore Locality","displayName":"Ignore Locality","identifiesControllerService":false,"sensitive":false},"Kerberos Principal":{"name":"Kerberos Principal","displayName":"Kerberos Principal","identifiesControllerService":false,"sensitive":false},"Replication":{"name":"Replication","displayName":"Replication","identifiesControllerService":false,"sensitive":false},"kerberos-user-service":{"name":"kerberos-user-service","displayName":"Kerberos User Service","identifiesControllerService":true,"sensitive":false},"writing-strategy":{"name":"writing-strategy","displayName":"Writing Strategy","identifiesControllerService":false,"sensitive":false},"Kerberos Relogin Period":{"name":"Kerberos Relogin Period","displayName":"Kerberos Relogin Period","identifiesControllerService":false,"sensitive":false},"Directory":{"name":"Directory","displayName":"Directory","identifiesControllerService":false,"sensitive":false},"Conflict Resolution Strategy":{"name":"Conflict Resolution Strategy","displayName":"Conflict Resolution Strategy","identifiesControllerService":false,"sensitive":false}},"style":{},"schedulingPeriod":"0 sec","schedulingStrategy":"TIMER_DRIVEN","executionNode":"ALL","penaltyDuration":"30 sec","yieldDuration":"1 sec","bulletinLevel":"WARN","runDurationMillis":0,"concurrentlySchedulableTaskCount":1,"autoTerminatedRelationships":["success"],"scheduledState":"ENABLED","retryCount":0,"retriedRelationships":[],"backoffMechanism":"PENALIZE_FLOWFILE","maxBackoffPeriod":"10 mins","componentType":"PROCESSOR","groupIdentifier":"88c21c99-eba0-3bb8-800f-cba645bb9cb7"},{"identifier":"d7e2f55f-2b8f-395f-b07d-bcd2c91fc3a5","instanceIdentifier":"38922407-4b0c-3802-82ac-16c641d1ddbc","name":"Set Schema Name","comments":"","position":{"x":256.0,"y":888.0},"type":"org.apache.nifi.processors.attributes.UpdateAttribute","bundle":{"group":"org.apache.nifi","artifact":"nifi-update-attribute-nar","version":"1.23.1.2.1.6.0-323"},"properties":{"Delete Attributes Expression":null,"Store State":"Do not store state","canonical-value-lookup-cache-size":"100","schema.name":"CEF_events","Stateful Variables Initial Value":null},"propertyDescriptors":{"Delete Attributes Expression":{"name":"Delete Attributes Expression","displayName":"Delete Attributes Expression","identifiesControllerService":false,"sensitive":false},"Store State":{"name":"Store State","displayName":"Store State","identifiesControllerService":false,"sensitive":false},"canonical-value-lookup-cache-size":{"name":"canonical-value-lookup-cache-size","displayName":"Cache Value Lookup Cache Size","identifiesControllerService":false,"sensitive":false},"schema.name":{"name":"schema.name","displayName":"schema.name","identifiesControllerService":false,"sensitive":false},"Stateful Variables Initial Value":{"name":"Stateful Variables Initial Value","displayName":"Stateful Variables Initial Value","identifiesControllerService":false,"sensitive":false}},"style":{},"schedulingPeriod":"0 sec","schedulingStrategy":"TIMER_DRIVEN","executionNode":"ALL","penaltyDuration":"30 sec","yieldDuration":"1 sec","bulletinLevel":"WARN","runDurationMillis":0,"concurrentlySchedulableTaskCount":1,"autoTerminatedRelationships":[],"scheduledState":"ENABLED","retryCount":0,"retriedRelationships":[],"backoffMechanism":"PENALIZE_FLOWFILE","maxBackoffPeriod":"10 mins","componentType":"PROCESSOR","groupIdentifier":"88c21c99-eba0-3bb8-800f-cba645bb9cb7"},{"identifier":"16046290-3d25-3e89-b3e5-5ef5b8ac72ac","instanceIdentifier":"11e61928-5893-36b9-a518-c739f3ad332c","name":"ParseCEF","comments":"","position":{"x":256.0,"y":496.0},"type":"org.apache.nifi.processors.standard.ParseCEF","bundle":{"group":"org.apache.nifi","artifact":"nifi-standard-nar","version":"1.23.1.2.1.6.0-323"},"properties":{"VALIDATE_DATA":"true","APPEND_RAW_MESSAGE_TO_JSON":"true","TIME_REPRESENTATION":"Local Timezone (system Default)","INCLUDE_CUSTOM_EXTENSIONS":"false","FIELDS_DESTINATION":"flowfile-content","DATETIME_REPRESENTATION":"en-US","ACCEPT_EMPTY_EXTENSIONS":"false"},"propertyDescriptors":{"VALIDATE_DATA":{"name":"VALIDATE_DATA","displayName":"Validate the CEF event","identifiesControllerService":false,"sensitive":false},"APPEND_RAW_MESSAGE_TO_JSON":{"name":"APPEND_RAW_MESSAGE_TO_JSON","displayName":"Append raw message to JSON","identifiesControllerService":false,"sensitive":false},"TIME_REPRESENTATION":{"name":"TIME_REPRESENTATION","displayName":"Timezone","identifiesControllerService":false,"sensitive":false},"INCLUDE_CUSTOM_EXTENSIONS":{"name":"INCLUDE_CUSTOM_EXTENSIONS","displayName":"Include custom extensions","identifiesControllerService":false,"sensitive":false},"FIELDS_DESTINATION":{"name":"FIELDS_DESTINATION","displayName":"Parsed fields destination","identifiesControllerService":false,"sensitive":false},"DATETIME_REPRESENTATION":{"name":"DATETIME_REPRESENTATION","displayName":"DateTime Locale","identifiesControllerService":false,"sensitive":false},"ACCEPT_EMPTY_EXTENSIONS":{"name":"ACCEPT_EMPTY_EXTENSIONS","displayName":"Accept empty extensions","identifiesControllerService":false,"sensitive":false}},"style":{},"schedulingPeriod":"0 sec","schedulingStrategy":"TIMER_DRIVEN","executionNode":"ALL","penaltyDuration":"30 sec","yieldDuration":"1 sec","bulletinLevel":"WARN","runDurationMillis":0,"concurrentlySchedulableTaskCount":1,"autoTerminatedRelationships":[],"scheduledState":"ENABLED","retryCount":0,"retriedRelationships":[],"backoffMechanism":"PENALIZE_FLOWFILE","maxBackoffPeriod":"10 mins","componentType":"PROCESSOR","groupIdentifier":"88c21c99-eba0-3bb8-800f-cba645bb9cb7"},{"identifier":"926af61b-3fc7-3249-9679-7476bedd6dd1","instanceIdentifier":"f16bbbb1-5447-308b-a04d-5969a8143d54","name":"Convert to Avro","comments":"","position":{"x":256.0,"y":1640.0},"type":"org.apache.nifi.processors.standard.ConvertRecord","bundle":{"group":"org.apache.nifi","artifact":"nifi-standard-nar","version":"1.23.1.2.1.6.0-323"},"properties":{"record-writer":"d2bec69b-689d-3c20-a633-6f53ba2eff69","record-reader":"2224fa09-7305-3d59-838d-a39f264238aa","include-zero-record-flowfiles":"true"},"propertyDescriptors":{"record-writer":{"name":"record-writer","displayName":"Record Writer","identifiesControllerService":true,"sensitive":false},"record-reader":{"name":"record-reader","displayName":"Record Reader","identifiesControllerService":true,"sensitive":false},"include-zero-record-flowfiles":{"name":"include-zero-record-flowfiles","displayName":"Include Zero Record FlowFiles","identifiesControllerService":false,"sensitive":false}},"style":{},"schedulingPeriod":"0 sec","schedulingStrategy":"TIMER_DRIVEN","executionNode":"ALL","penaltyDuration":"30 sec","yieldDuration":"1 sec","bulletinLevel":"WARN","runDurationMillis":0,"concurrentlySchedulableTaskCount":1,"autoTerminatedRelationships":[],"scheduledState":"ENABLED","retryCount":0,"retriedRelationships":[],"backoffMechanism":"PENALIZE_FLOWFILE","maxBackoffPeriod":"10 mins","componentType":"PROCESSOR","groupIdentifier":"88c21c99-eba0-3bb8-800f-cba645bb9cb7"}],"inputPorts":[],"outputPorts":[],"connections":[{"identifier":"0b8e8426-b48d-3570-bf45-36bc65946dd0","instanceIdentifier":"def90a31-4d62-3daa-a847-5705e1bc93e6","name":"","source":{"id":"16046290-3d25-3e89-b3e5-5ef5b8ac72ac","type":"PROCESSOR","groupId":"88c21c99-eba0-3bb8-800f-cba645bb9cb7","name":"ParseCEF","comments":"","instanceIdentifier":"11e61928-5893-36b9-a518-c739f3ad332c"},"destination":{"id":"f18e1d79-c52f-3635-9305-16ff4f1b2815","type":"PROCESSOR","groupId":"88c21c99-eba0-3bb8-800f-cba645bb9cb7","name":"JoltTransformJSON","comments":"","instanceIdentifier":"1f9ccd80-84ba-3fa3-8efb-f2572a767f00"},"labelIndex":1,"zIndex":0,"selectedRelationships":["success"],"backPressureObjectThreshold":10000,"backPressureDataSizeThreshold":"1 GB","flowFileExpiration":"0 sec","prioritizers":[],"bends":[],"loadBalanceStrategy":"DO_NOT_LOAD_BALANCE","partitioningAttribute":"","loadBalanceCompression":"DO_NOT_COMPRESS","componentType":"CONNECTION","groupIdentifier":"88c21c99-eba0-3bb8-800f-cba645bb9cb7"},{"identifier":"9018ba2d-bad3-3ec0-ab26-4cb7a3583032","instanceIdentifier":"ec9dd4b8-bea9-33f1-b6f8-2fefd4efd81b","name":"","source":{"id":"2b613617-9897-3023-8778-add667fb99e6","type":"PROCESSOR","groupId":"88c21c99-eba0-3bb8-800f-cba645bb9cb7","name":"Re-route Time Errors","comments":"","instanceIdentifier":"883a05d6-e964-3149-8284-d504932eefb1"},"destination":{"id":"fa610e3a-cfda-3a64-a3d5-943f0ae42338","type":"PROCESSOR","groupId":"88c21c99-eba0-3bb8-800f-cba645bb9cb7","name":"PutHive3Streaming","comments":"","instanceIdentifier":"990d9023-ce1f-32cf-9434-0026ca43c7db"},"labelIndex":1,"zIndex":0,"selectedRelationships":["unmatched"],"backPressureObjectThreshold":10000,"backPressureDataSizeThreshold":"1 GB","flowFileExpiration":"0 sec","prioritizers":[],"bends":[],"loadBalanceStrategy":"DO_NOT_LOAD_BALANCE","partitioningAttribute":"","loadBalanceCompression":"DO_NOT_COMPRESS","componentType":"CONNECTION","groupIdentifier":"88c21c99-eba0-3bb8-800f-cba645bb9cb7"},{"identifier":"f36fa622-59ff-3bb1-bf48-6ddb7fae33db","instanceIdentifier":"7b4ec3b4-62d3-37cd-bfd8-943fb2610f24","name":"","source":{"id":"2b613617-9897-3023-8778-add667fb99e6","type":"PROCESSOR","groupId":"88c21c99-eba0-3bb8-800f-cba645bb9cb7","name":"Re-route Time Errors","comments":"","instanceIdentifier":"883a05d6-e964-3149-8284-d504932eefb1"},"destination":{"id":"926af61b-3fc7-3249-9679-7476bedd6dd1","type":"PROCESSOR","groupId":"88c21c99-eba0-3bb8-800f-cba645bb9cb7","name":"Convert to Avro","comments":"","instanceIdentifier":"f16bbbb1-5447-308b-a04d-5969a8143d54"},"labelIndex":1,"zIndex":0,"selectedRelationships":["unmatched"],"backPressureObjectThreshold":10000,"backPressureDataSizeThreshold":"1 GB","flowFileExpiration":"0 sec","prioritizers":[],"bends":[],"loadBalanceStrategy":"DO_NOT_LOAD_BALANCE","partitioningAttribute":"","loadBalanceCompression":"DO_NOT_COMPRESS","componentType":"CONNECTION","groupIdentifier":"88c21c99-eba0-3bb8-800f-cba645bb9cb7"},{"identifier":"5ee8257e-a2be-3a69-beae-0b428205a2f9","instanceIdentifier":"bc9fbcf0-257a-3cca-bf24-930045dc0c6e","name":"","source":{"id":"fa610e3a-cfda-3a64-a3d5-943f0ae42338","type":"PROCESSOR","groupId":"88c21c99-eba0-3bb8-800f-cba645bb9cb7","name":"PutHive3Streaming","comments":"","instanceIdentifier":"990d9023-ce1f-32cf-9434-0026ca43c7db"},"destination":{"id":"fa610e3a-cfda-3a64-a3d5-943f0ae42338","type":"PROCESSOR","groupId":"88c21c99-eba0-3bb8-800f-cba645bb9cb7","name":"PutHive3Streaming","comments":"","instanceIdentifier":"990d9023-ce1f-32cf-9434-0026ca43c7db"},"labelIndex":1,"zIndex":0,"selectedRelationships":["retry"],"backPressureObjectThreshold":10000,"backPressureDataSizeThreshold":"1 GB","flowFileExpiration":"0 sec","prioritizers":[],"bends":[{"x":1229.6154556274414,"y":1851.744140625},{"x":1229.6154556274414,"y":1901.744140625}],"loadBalanceStrategy":"DO_NOT_LOAD_BALANCE","partitioningAttribute":"","loadBalanceCompression":"DO_NOT_COMPRESS","componentType":"CONNECTION","groupIdentifier":"88c21c99-eba0-3bb8-800f-cba645bb9cb7"},{"identifier":"762ba61c-7b6d-30b9-89ab-48daeee1882c","instanceIdentifier":"e1360116-6d97-33eb-9328-aeee20aed781","name":"","source":{"id":"4e6d6623-b49d-3e0e-9b5b-f0e20150c594","type":"PROCESSOR","groupId":"88c21c99-eba0-3bb8-800f-cba645bb9cb7","name":"ReplaceText","comments":"","instanceIdentifier":"f1c9e653-9c56-3626-96e3-625baaac4422"},"destination":{"id":"43710b2a-0a9d-36c6-b62f-7d8e89c0786a","type":"PROCESSOR","groupId":"88c21c99-eba0-3bb8-800f-cba645bb9cb7","name":"RegEx Capture CEF-Ambiguous Values ","comments":"","instanceIdentifier":"2fa47dbd-f6f2-3bbe-80aa-74f501b2050a"},"labelIndex":1,"zIndex":0,"selectedRelationships":["success"],"backPressureObjectThreshold":10000,"backPressureDataSizeThreshold":"1 GB","flowFileExpiration":"0 sec","prioritizers":[],"bends":[],"loadBalanceStrategy":"DO_NOT_LOAD_BALANCE","partitioningAttribute":"","loadBalanceCompression":"DO_NOT_COMPRESS","componentType":"CONNECTION","groupIdentifier":"88c21c99-eba0-3bb8-800f-cba645bb9cb7"},{"identifier":"98e663ed-a65f-3daf-87a8-9a5fbb63451c","instanceIdentifier":"ddb80fb3-d0c2-3a7f-b5e5-53fa2d40d4ed","name":"","source":{"id":"5981c418-68ab-37ed-b996-c163955afcea","type":"PROCESSOR","groupId":"88c21c99-eba0-3bb8-800f-cba645bb9cb7","name":"Subscribe to MQTT","comments":"","instanceIdentifier":"66ff78a4-7320-3dc3-a59f-8c19c0abe017"},"destination":{"id":"82151105-1bef-3692-84b0-fa173ae82c31","type":"PROCESSOR","groupId":"88c21c99-eba0-3bb8-800f-cba645bb9cb7","name":"Publish Device Logs to Kafka","comments":"","instanceIdentifier":"6fe5ba4d-c0df-30ab-9ad0-f4b2d950fe2c"},"labelIndex":1,"zIndex":0,"selectedRelationships":["Message"],"backPressureObjectThreshold":10000,"backPressureDataSizeThreshold":"1 GB","flowFileExpiration":"0 sec","prioritizers":[],"bends":[],"loadBalanceStrategy":"DO_NOT_LOAD_BALANCE","partitioningAttribute":"","loadBalanceCompression":"DO_NOT_COMPRESS","componentType":"CONNECTION","groupIdentifier":"88c21c99-eba0-3bb8-800f-cba645bb9cb7"},{"identifier":"0ff57628-2b48-3e81-af68-7f13166d7d07","instanceIdentifier":"770d2c76-19b2-3a1a-80fe-debd8335fddd","name":"","source":{"id":"d7e2f55f-2b8f-395f-b07d-bcd2c91fc3a5","type":"PROCESSOR","groupId":"88c21c99-eba0-3bb8-800f-cba645bb9cb7","name":"Set Schema Name","comments":"","instanceIdentifier":"38922407-4b0c-3802-82ac-16c641d1ddbc"},"destination":{"id":"89292f75-832f-3e9b-8892-e19374175803","type":"PROCESSOR","groupId":"88c21c99-eba0-3bb8-800f-cba645bb9cb7","name":"Transforms","comments":"","instanceIdentifier":"46d14641-dccf-3e84-8012-dc6574026209"},"labelIndex":1,"zIndex":0,"selectedRelationships":["success"],"backPressureObjectThreshold":10000,"backPressureDataSizeThreshold":"1 GB","flowFileExpiration":"0 sec","prioritizers":[],"bends":[],"loadBalanceStrategy":"DO_NOT_LOAD_BALANCE","partitioningAttribute":"","loadBalanceCompression":"DO_NOT_COMPRESS","componentType":"CONNECTION","groupIdentifier":"88c21c99-eba0-3bb8-800f-cba645bb9cb7"},{"identifier":"05e3cb68-999a-3e65-9613-65988cb32100","instanceIdentifier":"354f1ebe-b352-389b-873b-2c5b62fea5fb","name":"","source":{"id":"43710b2a-0a9d-36c6-b62f-7d8e89c0786a","type":"PROCESSOR","groupId":"88c21c99-eba0-3bb8-800f-cba645bb9cb7","name":"RegEx Capture CEF-Ambiguous Values ","comments":"","instanceIdentifier":"2fa47dbd-f6f2-3bbe-80aa-74f501b2050a"},"destination":{"id":"16046290-3d25-3e89-b3e5-5ef5b8ac72ac","type":"PROCESSOR","groupId":"88c21c99-eba0-3bb8-800f-cba645bb9cb7","name":"ParseCEF","comments":"","instanceIdentifier":"11e61928-5893-36b9-a518-c739f3ad332c"},"labelIndex":1,"zIndex":0,"selectedRelationships":["matched"],"backPressureObjectThreshold":10000,"backPressureDataSizeThreshold":"1 GB","flowFileExpiration":"0 sec","prioritizers":[],"bends":[],"loadBalanceStrategy":"DO_NOT_LOAD_BALANCE","partitioningAttribute":"","loadBalanceCompression":"DO_NOT_COMPRESS","componentType":"CONNECTION","groupIdentifier":"88c21c99-eba0-3bb8-800f-cba645bb9cb7"},{"identifier":"23f2874d-cff9-3eca-b814-63a85ba865af","instanceIdentifier":"27f159d5-9033-3a11-b6d7-e1a81d0dd896","name":"","source":{"id":"f18e1d79-c52f-3635-9305-16ff4f1b2815","type":"PROCESSOR","groupId":"88c21c99-eba0-3bb8-800f-cba645bb9cb7","name":"JoltTransformJSON","comments":"","instanceIdentifier":"1f9ccd80-84ba-3fa3-8efb-f2572a767f00"},"destination":{"id":"2c251fec-e94c-3420-98ee-d1989813fd7c","type":"FUNNEL","groupId":"88c21c99-eba0-3bb8-800f-cba645bb9cb7","name":"Funnel","comments":"","instanceIdentifier":"e15af3e2-ae31-3e11-9f26-7fdd583ffa3f"},"labelIndex":1,"zIndex":0,"selectedRelationships":["failure"],"backPressureObjectThreshold":10000,"backPressureDataSizeThreshold":"1 GB","flowFileExpiration":"0 sec","prioritizers":[],"bends":[],"loadBalanceStrategy":"DO_NOT_LOAD_BALANCE","partitioningAttribute":"","loadBalanceCompression":"DO_NOT_COMPRESS","componentType":"CONNECTION","groupIdentifier":"88c21c99-eba0-3bb8-800f-cba645bb9cb7"},{"identifier":"5630b601-4d04-33ba-8228-af5ae45152bc","instanceIdentifier":"ea0c0762-539f-3084-9c60-ff41105c439e","name":"","source":{"id":"89292f75-832f-3e9b-8892-e19374175803","type":"PROCESSOR","groupId":"88c21c99-eba0-3bb8-800f-cba645bb9cb7","name":"Transforms","comments":"","instanceIdentifier":"46d14641-dccf-3e84-8012-dc6574026209"},"destination":{"id":"a2c8d1dd-8f03-3af7-a745-621b04cb33a8","type":"PROCESSOR","groupId":"88c21c99-eba0-3bb8-800f-cba645bb9cb7","name":"Lookup Geo","comments":"","instanceIdentifier":"01459cc0-e594-3da6-98cd-384a8997b0d3"},"labelIndex":1,"zIndex":0,"selectedRelationships":["success"],"backPressureObjectThreshold":10000,"backPressureDataSizeThreshold":"1 GB","flowFileExpiration":"0 sec","prioritizers":[],"bends":[],"loadBalanceStrategy":"DO_NOT_LOAD_BALANCE","partitioningAttribute":"","loadBalanceCompression":"DO_NOT_COMPRESS","componentType":"CONNECTION","groupIdentifier":"88c21c99-eba0-3bb8-800f-cba645bb9cb7"},{"identifier":"d09b97df-f609-30ba-8652-71ff434e74aa","instanceIdentifier":"dcc2265a-768f-38b8-8ea4-d3a852b4ec01","name":"","source":{"id":"926af61b-3fc7-3249-9679-7476bedd6dd1","type":"PROCESSOR","groupId":"88c21c99-eba0-3bb8-800f-cba645bb9cb7","name":"Convert to Avro","comments":"","instanceIdentifier":"f16bbbb1-5447-308b-a04d-5969a8143d54"},"destination":{"id":"c82a21f9-eb14-3435-99d5-0eb34d08abf3","type":"PROCESSOR","groupId":"88c21c99-eba0-3bb8-800f-cba645bb9cb7","name":"PutHDFS","comments":"","instanceIdentifier":"c6a18fd6-afb7-3b8a-935f-c0c793c2b27a"},"labelIndex":1,"zIndex":0,"selectedRelationships":["success"],"backPressureObjectThreshold":10000,"backPressureDataSizeThreshold":"1 GB","flowFileExpiration":"0 sec","prioritizers":[],"bends":[],"loadBalanceStrategy":"DO_NOT_LOAD_BALANCE","partitioningAttribute":"","loadBalanceCompression":"DO_NOT_COMPRESS","componentType":"CONNECTION","groupIdentifier":"88c21c99-eba0-3bb8-800f-cba645bb9cb7"},{"identifier":"50238f63-5665-31f2-aea2-dcb17b707dfe","instanceIdentifier":"783fe91f-574e-37b3-9371-3321bd2ab900","name":"","source":{"id":"f18e1d79-c52f-3635-9305-16ff4f1b2815","type":"PROCESSOR","groupId":"88c21c99-eba0-3bb8-800f-cba645bb9cb7","name":"JoltTransformJSON","comments":"","instanceIdentifier":"1f9ccd80-84ba-3fa3-8efb-f2572a767f00"},"destination":{"id":"d7e2f55f-2b8f-395f-b07d-bcd2c91fc3a5","type":"PROCESSOR","groupId":"88c21c99-eba0-3bb8-800f-cba645bb9cb7","name":"Set Schema Name","comments":"","instanceIdentifier":"38922407-4b0c-3802-82ac-16c641d1ddbc"},"labelIndex":1,"zIndex":0,"selectedRelationships":["success"],"backPressureObjectThreshold":10000,"backPressureDataSizeThreshold":"1 GB","flowFileExpiration":"0 sec","prioritizers":[],"bends":[],"loadBalanceStrategy":"DO_NOT_LOAD_BALANCE","partitioningAttribute":"","loadBalanceCompression":"DO_NOT_COMPRESS","componentType":"CONNECTION","groupIdentifier":"88c21c99-eba0-3bb8-800f-cba645bb9cb7"},{"identifier":"7f97d553-1cc3-3103-95b0-ff7a188af20d","instanceIdentifier":"b14722f1-0a75-355e-8c3e-23c124f2e289","name":"","source":{"id":"a2c8d1dd-8f03-3af7-a745-621b04cb33a8","type":"PROCESSOR","groupId":"88c21c99-eba0-3bb8-800f-cba645bb9cb7","name":"Lookup Geo","comments":"","instanceIdentifier":"01459cc0-e594-3da6-98cd-384a8997b0d3"},"destination":{"id":"69c7f30d-97c6-3dc1-8dc0-5d7b95e12eba","type":"FUNNEL","groupId":"88c21c99-eba0-3bb8-800f-cba645bb9cb7","name":"Funnel","comments":"","instanceIdentifier":"4adc9683-08ab-36cc-ada0-6af7b2da1c4d"},"labelIndex":1,"zIndex":0,"selectedRelationships":["failure"],"backPressureObjectThreshold":10000,"backPressureDataSizeThreshold":"1 GB","flowFileExpiration":"0 sec","prioritizers":[],"bends":[],"loadBalanceStrategy":"DO_NOT_LOAD_BALANCE","partitioningAttribute":"","loadBalanceCompression":"DO_NOT_COMPRESS","componentType":"CONNECTION","groupIdentifier":"88c21c99-eba0-3bb8-800f-cba645bb9cb7"},{"identifier":"9aa49fa9-157f-3a65-b6de-6c5910965ee4","instanceIdentifier":"122f7d20-61b2-3d2f-965f-a5778078f781","name":"","source":{"id":"16046290-3d25-3e89-b3e5-5ef5b8ac72ac","type":"PROCESSOR","groupId":"88c21c99-eba0-3bb8-800f-cba645bb9cb7","name":"ParseCEF","comments":"","instanceIdentifier":"11e61928-5893-36b9-a518-c739f3ad332c"},"destination":{"id":"2c251fec-e94c-3420-98ee-d1989813fd7c","type":"FUNNEL","groupId":"88c21c99-eba0-3bb8-800f-cba645bb9cb7","name":"Funnel","comments":"","instanceIdentifier":"e15af3e2-ae31-3e11-9f26-7fdd583ffa3f"},"labelIndex":1,"zIndex":0,"selectedRelationships":["failure"],"backPressureObjectThreshold":10000,"backPressureDataSizeThreshold":"1 GB","flowFileExpiration":"0 sec","prioritizers":[],"bends":[],"loadBalanceStrategy":"DO_NOT_LOAD_BALANCE","partitioningAttribute":"","loadBalanceCompression":"DO_NOT_COMPRESS","componentType":"CONNECTION","groupIdentifier":"88c21c99-eba0-3bb8-800f-cba645bb9cb7"},{"identifier":"06791311-f4b1-3c63-a1d5-bb46cd59b7b0","instanceIdentifier":"3648d666-7d97-3bab-8e44-06f6383eeaef","name":"","source":{"id":"c82a21f9-eb14-3435-99d5-0eb34d08abf3","type":"PROCESSOR","groupId":"88c21c99-eba0-3bb8-800f-cba645bb9cb7","name":"PutHDFS","comments":"","instanceIdentifier":"c6a18fd6-afb7-3b8a-935f-c0c793c2b27a"},"destination":{"id":"b68a0d96-faeb-3f79-8eb5-9eace53abcad","type":"FUNNEL","groupId":"88c21c99-eba0-3bb8-800f-cba645bb9cb7","name":"Funnel","comments":"","instanceIdentifier":"790c452c-f0ed-37cf-9ddf-b00e044b3362"},"labelIndex":1,"zIndex":0,"selectedRelationships":["failure"],"backPressureObjectThreshold":10000,"backPressureDataSizeThreshold":"1 GB","flowFileExpiration":"0 sec","prioritizers":[],"bends":[],"loadBalanceStrategy":"DO_NOT_LOAD_BALANCE","partitioningAttribute":"","loadBalanceCompression":"DO_NOT_COMPRESS","componentType":"CONNECTION","groupIdentifier":"88c21c99-eba0-3bb8-800f-cba645bb9cb7"},{"identifier":"b6fe845d-24b5-3a26-b74e-f7a27bc12583","instanceIdentifier":"d47f8622-bdc1-303a-91d9-8093807fb407","name":"","source":{"id":"a2c8d1dd-8f03-3af7-a745-621b04cb33a8","type":"PROCESSOR","groupId":"88c21c99-eba0-3bb8-800f-cba645bb9cb7","name":"Lookup Geo","comments":"","instanceIdentifier":"01459cc0-e594-3da6-98cd-384a8997b0d3"},"destination":{"id":"2b613617-9897-3023-8778-add667fb99e6","type":"PROCESSOR","groupId":"88c21c99-eba0-3bb8-800f-cba645bb9cb7","name":"Re-route Time Errors","comments":"","instanceIdentifier":"883a05d6-e964-3149-8284-d504932eefb1"},"labelIndex":1,"zIndex":0,"selectedRelationships":["success"],"backPressureObjectThreshold":10000,"backPressureDataSizeThreshold":"1 GB","flowFileExpiration":"0 sec","prioritizers":[],"bends":[],"loadBalanceStrategy":"DO_NOT_LOAD_BALANCE","partitioningAttribute":"","loadBalanceCompression":"DO_NOT_COMPRESS","componentType":"CONNECTION","groupIdentifier":"88c21c99-eba0-3bb8-800f-cba645bb9cb7"},{"identifier":"979f3ebc-397d-3d4a-8be7-a0d678b7cdbc","instanceIdentifier":"d3781591-7755-3953-96aa-7b86570dc644","name":"","source":{"id":"89292f75-832f-3e9b-8892-e19374175803","type":"PROCESSOR","groupId":"88c21c99-eba0-3bb8-800f-cba645bb9cb7","name":"Transforms","comments":"","instanceIdentifier":"46d14641-dccf-3e84-8012-dc6574026209"},"destination":{"id":"2c251fec-e94c-3420-98ee-d1989813fd7c","type":"FUNNEL","groupId":"88c21c99-eba0-3bb8-800f-cba645bb9cb7","name":"Funnel","comments":"","instanceIdentifier":"e15af3e2-ae31-3e11-9f26-7fdd583ffa3f"},"labelIndex":1,"zIndex":0,"selectedRelationships":["failure"],"backPressureObjectThreshold":10000,"backPressureDataSizeThreshold":"1 GB","flowFileExpiration":"0 sec","prioritizers":[],"bends":[],"loadBalanceStrategy":"DO_NOT_LOAD_BALANCE","partitioningAttribute":"","loadBalanceCompression":"DO_NOT_COMPRESS","componentType":"CONNECTION","groupIdentifier":"88c21c99-eba0-3bb8-800f-cba645bb9cb7"},{"identifier":"7ed09a3e-3b43-3b35-8081-5e9949b99b79","instanceIdentifier":"267842e8-f2af-3a7d-a068-daaefd6dc159","name":"","source":{"id":"36fcc2dd-6e55-3970-9c63-03c5b6663ec4","type":"PROCESSOR","groupId":"88c21c99-eba0-3bb8-800f-cba645bb9cb7","name":"Subscribe to Kafka CEF Logs","comments":"","instanceIdentifier":"25b33c8e-f942-3979-8f2f-a4b5b8e88803"},"destination":{"id":"ad33cf8f-626b-324c-a459-6b0f8380eebf","type":"PROCESSOR","groupId":"88c21c99-eba0-3bb8-800f-cba645bb9cb7","name":"PutHDFS","comments":"","instanceIdentifier":"c714889c-5716-3c90-9a4d-db2c62fad4f0"},"labelIndex":1,"zIndex":0,"selectedRelationships":["success"],"backPressureObjectThreshold":10000,"backPressureDataSizeThreshold":"1 GB","flowFileExpiration":"0 sec","prioritizers":[],"bends":[],"loadBalanceStrategy":"DO_NOT_LOAD_BALANCE","partitioningAttribute":"","loadBalanceCompression":"DO_NOT_COMPRESS","componentType":"CONNECTION","groupIdentifier":"88c21c99-eba0-3bb8-800f-cba645bb9cb7"},{"identifier":"98e40b45-b73e-3504-b674-78f78b6216e2","instanceIdentifier":"064684ce-4fb9-37c1-9e91-47931ec482a4","name":"","source":{"id":"926af61b-3fc7-3249-9679-7476bedd6dd1","type":"PROCESSOR","groupId":"88c21c99-eba0-3bb8-800f-cba645bb9cb7","name":"Convert to Avro","comments":"","instanceIdentifier":"f16bbbb1-5447-308b-a04d-5969a8143d54"},"destination":{"id":"69c7f30d-97c6-3dc1-8dc0-5d7b95e12eba","type":"FUNNEL","groupId":"88c21c99-eba0-3bb8-800f-cba645bb9cb7","name":"Funnel","comments":"","instanceIdentifier":"4adc9683-08ab-36cc-ada0-6af7b2da1c4d"},"labelIndex":1,"zIndex":0,"selectedRelationships":["failure"],"backPressureObjectThreshold":10000,"backPressureDataSizeThreshold":"1 GB","flowFileExpiration":"0 sec","prioritizers":[],"bends":[],"loadBalanceStrategy":"DO_NOT_LOAD_BALANCE","partitioningAttribute":"","loadBalanceCompression":"DO_NOT_COMPRESS","componentType":"CONNECTION","groupIdentifier":"88c21c99-eba0-3bb8-800f-cba645bb9cb7"},{"identifier":"c5032dd8-b24a-3e6e-9947-8d5b057275c8","instanceIdentifier":"e1662ae5-573f-3c8e-a9d0-62ab1f3f0094","name":"","source":{"id":"43710b2a-0a9d-36c6-b62f-7d8e89c0786a","type":"PROCESSOR","groupId":"88c21c99-eba0-3bb8-800f-cba645bb9cb7","name":"RegEx Capture CEF-Ambiguous Values ","comments":"","instanceIdentifier":"2fa47dbd-f6f2-3bbe-80aa-74f501b2050a"},"destination":{"id":"2c251fec-e94c-3420-98ee-d1989813fd7c","type":"FUNNEL","groupId":"88c21c99-eba0-3bb8-800f-cba645bb9cb7","name":"Funnel","comments":"","instanceIdentifier":"e15af3e2-ae31-3e11-9f26-7fdd583ffa3f"},"labelIndex":1,"zIndex":0,"selectedRelationships":["unmatched"],"backPressureObjectThreshold":10000,"backPressureDataSizeThreshold":"1 GB","flowFileExpiration":"0 sec","prioritizers":[],"bends":[],"loadBalanceStrategy":"DO_NOT_LOAD_BALANCE","partitioningAttribute":"","loadBalanceCompression":"DO_NOT_COMPRESS","componentType":"CONNECTION","groupIdentifier":"88c21c99-eba0-3bb8-800f-cba645bb9cb7"},{"identifier":"3687e0a7-ae50-3363-b32c-313f75283969","instanceIdentifier":"d3fcd1cf-ea64-3934-b80a-8872e1eddbc0","name":"","source":{"id":"2b613617-9897-3023-8778-add667fb99e6","type":"PROCESSOR","groupId":"88c21c99-eba0-3bb8-800f-cba645bb9cb7","name":"Re-route Time Errors","comments":"","instanceIdentifier":"883a05d6-e964-3149-8284-d504932eefb1"},"destination":{"id":"69c7f30d-97c6-3dc1-8dc0-5d7b95e12eba","type":"FUNNEL","groupId":"88c21c99-eba0-3bb8-800f-cba645bb9cb7","name":"Funnel","comments":"","instanceIdentifier":"4adc9683-08ab-36cc-ada0-6af7b2da1c4d"},"labelIndex":1,"zIndex":0,"selectedRelationships":["time.exception"],"backPressureObjectThreshold":10000,"backPressureDataSizeThreshold":"1 GB","flowFileExpiration":"0 sec","prioritizers":[],"bends":[],"loadBalanceStrategy":"DO_NOT_LOAD_BALANCE","partitioningAttribute":"","loadBalanceCompression":"DO_NOT_COMPRESS","componentType":"CONNECTION","groupIdentifier":"88c21c99-eba0-3bb8-800f-cba645bb9cb7"},{"identifier":"06fa1dc8-4ffe-3404-8174-6114a2ec9b53","instanceIdentifier":"08d59b52-1571-3031-8241-48473491b771","name":"","source":{"id":"36fcc2dd-6e55-3970-9c63-03c5b6663ec4","type":"PROCESSOR","groupId":"88c21c99-eba0-3bb8-800f-cba645bb9cb7","name":"Subscribe to Kafka CEF Logs","comments":"","instanceIdentifier":"25b33c8e-f942-3979-8f2f-a4b5b8e88803"},"destination":{"id":"4e6d6623-b49d-3e0e-9b5b-f0e20150c594","type":"PROCESSOR","groupId":"88c21c99-eba0-3bb8-800f-cba645bb9cb7","name":"ReplaceText","comments":"","instanceIdentifier":"f1c9e653-9c56-3626-96e3-625baaac4422"},"labelIndex":1,"zIndex":0,"selectedRelationships":["success"],"backPressureObjectThreshold":10000,"backPressureDataSizeThreshold":"1 GB","flowFileExpiration":"0 sec","prioritizers":[],"bends":[],"loadBalanceStrategy":"DO_NOT_LOAD_BALANCE","partitioningAttribute":"","loadBalanceCompression":"DO_NOT_COMPRESS","componentType":"CONNECTION","groupIdentifier":"88c21c99-eba0-3bb8-800f-cba645bb9cb7"}],"labels":[{"identifier":"05df58d0-705e-3188-abc0-8cc270a47430","instanceIdentifier":"955d6112-31a0-35ed-b16b-35f9453ca8a1","position":{"x":696.0,"y":-64.0},"label":"CEF Producer Emulation","zIndex":0,"width":416.0,"height":696.0,"style":{"background-color":"#a2b39d","font-size":"22px"},"componentType":"LABEL","groupIdentifier":"88c21c99-eba0-3bb8-800f-cba645bb9cb7"}],"funnels":[{"identifier":"b68a0d96-faeb-3f79-8eb5-9eace53abcad","instanceIdentifier":"790c452c-f0ed-37cf-9ddf-b00e044b3362","position":{"x":600.0,"y":2048.0},"componentType":"FUNNEL","groupIdentifier":"88c21c99-eba0-3bb8-800f-cba645bb9cb7"},{"identifier":"2c251fec-e94c-3420-98ee-d1989813fd7c","instanceIdentifier":"e15af3e2-ae31-3e11-9f26-7fdd583ffa3f","position":{"x":-144.0,"y":696.0},"componentType":"FUNNEL","groupIdentifier":"88c21c99-eba0-3bb8-800f-cba645bb9cb7"},{"identifier":"69c7f30d-97c6-3dc1-8dc0-5d7b95e12eba","instanceIdentifier":"4adc9683-08ab-36cc-ada0-6af7b2da1c4d","position":{"x":-144.0,"y":1472.0},"componentType":"FUNNEL","groupIdentifier":"88c21c99-eba0-3bb8-800f-cba645bb9cb7"}],"controllerServices":[{"identifier":"dd72ffcb-a5af-3204-937a-7616b9c3b7d1","instanceIdentifier":"dc93074a-b50f-3fa1-8ce5-7a827e3f9585","name":"Event-JSON-Writer","comments":"","type":"org.apache.nifi.json.JsonRecordSetWriter","bundle":{"group":"org.apache.nifi","artifact":"nifi-record-serialization-services-nar","version":"1.23.1.2.1.6.0-323"},"properties":{"schema-branch":null,"compression-level":"1","schema-cache":null,"Timestamp Format":null,"Date Format":null,"Pretty Print JSON":"false","compression-format":"none","Schema Write Strategy":"hwx-schema-ref-attributes","suppress-nulls":"never-suppress","output-grouping":"output-array","schema-name":"${schema.name}","schema-registry":"48efdb85-9a78-3d93-8d5f-5ff3e823f9cb","Time Format":null,"schema-access-strategy":"schema-name","schema-protocol-version":"1","schema-version":null,"schema-text":"${avro.schema}"},"propertyDescriptors":{"schema-branch":{"name":"schema-branch","displayName":"Schema Branch","identifiesControllerService":false,"sensitive":false},"compression-level":{"name":"compression-level","displayName":"Compression Level","identifiesControllerService":false,"sensitive":false},"schema-cache":{"name":"schema-cache","displayName":"Schema Cache","identifiesControllerService":true,"sensitive":false},"Timestamp Format":{"name":"Timestamp Format","displayName":"Timestamp Format","identifiesControllerService":false,"sensitive":false},"Date Format":{"name":"Date Format","displayName":"Date Format","identifiesControllerService":false,"sensitive":false},"Pretty Print JSON":{"name":"Pretty Print JSON","displayName":"Pretty Print JSON","identifiesControllerService":false,"sensitive":false},"compression-format":{"name":"compression-format","displayName":"Compression Format","identifiesControllerService":false,"sensitive":false},"Schema Write Strategy":{"name":"Schema Write Strategy","displayName":"Schema Write Strategy","identifiesControllerService":false,"sensitive":false},"suppress-nulls":{"name":"suppress-nulls","displayName":"Suppress Null Values","identifiesControllerService":false,"sensitive":false},"output-grouping":{"name":"output-grouping","displayName":"Output Grouping","identifiesControllerService":false,"sensitive":false},"schema-name":{"name":"schema-name","displayName":"Schema Name","identifiesControllerService":false,"sensitive":false},"schema-registry":{"name":"schema-registry","displayName":"Schema Registry","identifiesControllerService":true,"sensitive":false},"Time Format":{"name":"Time Format","displayName":"Time Format","identifiesControllerService":false,"sensitive":false},"schema-access-strategy":{"name":"schema-access-strategy","displayName":"Schema Access Strategy","identifiesControllerService":false,"sensitive":false},"schema-protocol-version":{"name":"schema-protocol-version","displayName":"Schema Protocol Version","identifiesControllerService":false,"sensitive":false},"schema-version":{"name":"schema-version","displayName":"Schema Version","identifiesControllerService":false,"sensitive":false},"schema-text":{"name":"schema-text","displayName":"Schema Text","identifiesControllerService":false,"sensitive":false}},"controllerServiceApis":[{"type":"org.apache.nifi.serialization.RecordSetWriterFactory","bundle":{"group":"org.apache.nifi","artifact":"nifi-standard-services-api-nar","version":"1.23.1.2.1.6.0-323"}}],"scheduledState":"DISABLED","bulletinLevel":"WARN","componentType":"CONTROLLER_SERVICE","groupIdentifier":"88c21c99-eba0-3bb8-800f-cba645bb9cb7"},{"identifier":"6d8d4783-336d-319d-b2ce-11b8462f0bbb","instanceIdentifier":"2b414c99-8c75-3630-851f-0800404f91c8","name":"DatabaseRecordLookupService","comments":"","type":"org.apache.nifi.lookup.db.DatabaseRecordLookupService","bundle":{"group":"org.apache.nifi","artifact":"nifi-lookup-services-nar","version":"1.23.1.2.1.6.0-323"},"properties":{"dbrecord-lookup-dbcp-service":"ff6473fe-7774-3fbe-8bc8-9fa4ab859cb8","dbf-default-precision":"10","dbrecord-lookup-clear-cache-on-enabled":"true","dbrecord-lookup-cache-size":"12","dbrecord-lookup-value-columns":"latitude,longitude","dbrecord-lookup-key-column":"locations","Cache Expiration":null,"dbf-default-scale":"10","dbrecord-lookup-table-name":"default.location_lkp"},"propertyDescriptors":{"dbrecord-lookup-dbcp-service":{"name":"dbrecord-lookup-dbcp-service","displayName":"Database Connection Pooling Service","identifiesControllerService":true,"sensitive":false},"dbf-default-precision":{"name":"dbf-default-precision","displayName":"Default Decimal Precision","identifiesControllerService":false,"sensitive":false},"dbrecord-lookup-clear-cache-on-enabled":{"name":"dbrecord-lookup-clear-cache-on-enabled","displayName":"Clear Cache on Enabled","identifiesControllerService":false,"sensitive":false},"dbrecord-lookup-cache-size":{"name":"dbrecord-lookup-cache-size","displayName":"Cache Size","identifiesControllerService":false,"sensitive":false},"dbrecord-lookup-value-columns":{"name":"dbrecord-lookup-value-columns","displayName":"Lookup Value Columns","identifiesControllerService":false,"sensitive":false},"dbrecord-lookup-key-column":{"name":"dbrecord-lookup-key-column","displayName":"Lookup Key Column","identifiesControllerService":false,"sensitive":false},"Cache Expiration":{"name":"Cache Expiration","displayName":"Cache Expiration","identifiesControllerService":false,"sensitive":false},"dbf-default-scale":{"name":"dbf-default-scale","displayName":"Default Decimal Scale","identifiesControllerService":false,"sensitive":false},"dbrecord-lookup-table-name":{"name":"dbrecord-lookup-table-name","displayName":"Table Name","identifiesControllerService":false,"sensitive":false}},"controllerServiceApis":[{"type":"org.apache.nifi.lookup.RecordLookupService","bundle":{"group":"org.apache.nifi","artifact":"nifi-standard-services-api-nar","version":"1.23.1.2.1.6.0-323"}},{"type":"org.apache.nifi.lookup.LookupService","bundle":{"group":"org.apache.nifi","artifact":"nifi-standard-services-api-nar","version":"1.23.1.2.1.6.0-323"}}],"scheduledState":"DISABLED","bulletinLevel":"WARN","componentType":"CONTROLLER_SERVICE","groupIdentifier":"88c21c99-eba0-3bb8-800f-cba645bb9cb7"},{"identifier":"ff6473fe-7774-3fbe-8bc8-9fa4ab859cb8","instanceIdentifier":"8e6fc250-047f-30bc-b5b6-36d9d227cfff","name":"Hive-Conn-Pool","comments":"","type":"org.apache.nifi.dbcp.hive.Hive3ConnectionPool","bundle":{"group":"org.apache.nifi","artifact":"nifi-hive3-nar","version":"1.23.1.2.1.6.0-323"},"properties":{"dbcp-min-idle-conns":"0","dbcp-min-evictable-idle-time":"30 mins","hive-config-resources":"/etc/hive/conf.cloudera.hive/hive-site.xml,/etc/hive/conf.cloudera.hive/core-site.xml,/etc/hive/conf.cloudera.hive/hdfs-site.xml","kerberos-credentials-service":null,"dbcp-max-conn-lifetime":"-1","Validation-query":null,"Kerberos Keytab":null,"hive-max-total-connections":"8","dbcp-time-between-eviction-runs":"-1","hive-db-connect-url":"jdbc:hive2://3.144.230.228:10000/default","Kerberos Principal":null,"dbcp-soft-min-evictable-idle-time":"-1","hive-max-wait-time":"500 millis","dbcp-max-idle-conns":"8","hive-db-user":"admin"},"propertyDescriptors":{"dbcp-min-idle-conns":{"name":"dbcp-min-idle-conns","displayName":"Minimum Idle Connections","identifiesControllerService":false,"sensitive":false},"hive-db-password":{"name":"hive-db-password","displayName":"Password","identifiesControllerService":false,"sensitive":true},"dbcp-min-evictable-idle-time":{"name":"dbcp-min-evictable-idle-time","displayName":"Minimum Evictable Idle Time","identifiesControllerService":false,"sensitive":false},"hive-config-resources":{"name":"hive-config-resources","displayName":"Hive Configuration Resources","identifiesControllerService":false,"sensitive":false,"resourceDefinition":{"cardinality":"MULTIPLE","resourceTypes":["FILE"]}},"kerberos-credentials-service":{"name":"kerberos-credentials-service","displayName":"Kerberos Credentials Service","identifiesControllerService":true,"sensitive":false},"dbcp-max-conn-lifetime":{"name":"dbcp-max-conn-lifetime","displayName":"Max Connection Lifetime","identifiesControllerService":false,"sensitive":false},"Kerberos Password":{"name":"Kerberos Password","displayName":"Kerberos Password","identifiesControllerService":false,"sensitive":true},"Validation-query":{"name":"Validation-query","displayName":"Validation query","identifiesControllerService":false,"sensitive":false},"Kerberos Keytab":{"name":"Kerberos Keytab","displayName":"Kerberos Keytab","identifiesControllerService":false,"sensitive":false,"resourceDefinition":{"cardinality":"SINGLE","resourceTypes":["FILE"]}},"hive-max-total-connections":{"name":"hive-max-total-connections","displayName":"Max Total Connections","identifiesControllerService":false,"sensitive":false},"dbcp-time-between-eviction-runs":{"name":"dbcp-time-between-eviction-runs","displayName":"Time Between Eviction Runs","identifiesControllerService":false,"sensitive":false},"hive-db-connect-url":{"name":"hive-db-connect-url","displayName":"Database Connection URL","identifiesControllerService":false,"sensitive":false},"Kerberos Principal":{"name":"Kerberos Principal","displayName":"Kerberos Principal","identifiesControllerService":false,"sensitive":false},"dbcp-soft-min-evictable-idle-time":{"name":"dbcp-soft-min-evictable-idle-time","displayName":"Soft Minimum Evictable Idle Time","identifiesControllerService":false,"sensitive":false},"hive-max-wait-time":{"name":"hive-max-wait-time","displayName":"Max Wait Time","identifiesControllerService":false,"sensitive":false},"dbcp-max-idle-conns":{"name":"dbcp-max-idle-conns","displayName":"Max Idle Connections","identifiesControllerService":false,"sensitive":false},"hive-db-user":{"name":"hive-db-user","displayName":"Database User","identifiesControllerService":false,"sensitive":false}},"controllerServiceApis":[{"type":"org.apache.nifi.dbcp.hive.HiveDBCPService","bundle":{"group":"org.apache.nifi","artifact":"nifi-hive-services-api-nar","version":"1.23.1.2.1.6.0-323"}},{"type":"org.apache.nifi.dbcp.DBCPService","bundle":{"group":"org.apache.nifi","artifact":"nifi-standard-services-api-nar","version":"1.23.1.2.1.6.0-323"}},{"type":"org.apache.nifi.dbcp.hive.Hive3DBCPService","bundle":{"group":"org.apache.nifi","artifact":"nifi-hive-services-api-nar","version":"1.23.1.2.1.6.0-323"}}],"scheduledState":"DISABLED","bulletinLevel":"WARN","componentType":"CONTROLLER_SERVICE","groupIdentifier":"88c21c99-eba0-3bb8-800f-cba645bb9cb7"},{"identifier":"2c3df069-092b-3565-853f-d40814c9564a","instanceIdentifier":"9bf16c21-59e8-3bed-9239-2f56407e4714","name":"JSON-Reader-CEF_logging","comments":"","type":"org.apache.nifi.json.JsonTreeReader","bundle":{"group":"org.apache.nifi","artifact":"nifi-record-serialization-services-nar","version":"1.23.1.2.1.6.0-323"},"properties":{"schema-branch":null,"schema-application-strategy":"SELECTED_PART","Timestamp Format":null,"schema-inference-cache":null,"Date Format":null,"schema-name":"${schema.name}","starting-field-strategy":"ROOT_NODE","schema-registry":"48efdb85-9a78-3d93-8d5f-5ff3e823f9cb","starting-field-name":null,"Time Format":null,"schema-access-strategy":"schema-name","schema-version":null,"schema-text":"${avro.schema}"},"propertyDescriptors":{"schema-branch":{"name":"schema-branch","displayName":"Schema Branch","identifiesControllerService":false,"sensitive":false},"schema-application-strategy":{"name":"schema-application-strategy","displayName":"Schema Application Strategy","identifiesControllerService":false,"sensitive":false},"Timestamp Format":{"name":"Timestamp Format","displayName":"Timestamp Format","identifiesControllerService":false,"sensitive":false},"schema-inference-cache":{"name":"schema-inference-cache","displayName":"Schema Inference Cache","identifiesControllerService":true,"sensitive":false},"Date Format":{"name":"Date Format","displayName":"Date Format","identifiesControllerService":false,"sensitive":false},"schema-name":{"name":"schema-name","displayName":"Schema Name","identifiesControllerService":false,"sensitive":false},"starting-field-strategy":{"name":"starting-field-strategy","displayName":"Starting Field Strategy","identifiesControllerService":false,"sensitive":false},"schema-registry":{"name":"schema-registry","displayName":"Schema Registry","identifiesControllerService":true,"sensitive":false},"starting-field-name":{"name":"starting-field-name","displayName":"Starting Field Name","identifiesControllerService":false,"sensitive":false},"Time Format":{"name":"Time Format","displayName":"Time Format","identifiesControllerService":false,"sensitive":false},"schema-access-strategy":{"name":"schema-access-strategy","displayName":"Schema Access Strategy","identifiesControllerService":false,"sensitive":false},"schema-version":{"name":"schema-version","displayName":"Schema Version","identifiesControllerService":false,"sensitive":false},"schema-text":{"name":"schema-text","displayName":"Schema Text","identifiesControllerService":false,"sensitive":false}},"controllerServiceApis":[{"type":"org.apache.nifi.serialization.RecordReaderFactory","bundle":{"group":"org.apache.nifi","artifact":"nifi-standard-services-api-nar","version":"1.23.1.2.1.6.0-323"}}],"scheduledState":"DISABLED","bulletinLevel":"WARN","componentType":"CONTROLLER_SERVICE","groupIdentifier":"88c21c99-eba0-3bb8-800f-cba645bb9cb7"},{"identifier":"d2bec69b-689d-3c20-a633-6f53ba2eff69","instanceIdentifier":"d95a0c37-d703-3998-b2ce-52698dfc4f5e","name":"AvroRecordSetWriter","comments":"","type":"org.apache.nifi.avro.AvroRecordSetWriter","bundle":{"group":"org.apache.nifi","artifact":"nifi-record-serialization-services-nar","version":"1.23.1.2.1.6.0-323"},"properties":{"compression-format":"NONE","Schema Write Strategy":"avro-embedded","schema-branch":null,"schema-name":"${schema.name}","cache-size":"1000","schema-registry":"48efdb85-9a78-3d93-8d5f-5ff3e823f9cb","schema-access-strategy":"schema-name","schema-protocol-version":"1","schema-version":null,"encoder-pool-size":"32","schema-cache":null,"schema-text":"${avro.schema}"},"propertyDescriptors":{"compression-format":{"name":"compression-format","displayName":"Compression Format","identifiesControllerService":false,"sensitive":false},"Schema Write Strategy":{"name":"Schema Write Strategy","displayName":"Schema Write Strategy","identifiesControllerService":false,"sensitive":false},"schema-branch":{"name":"schema-branch","displayName":"Schema Branch","identifiesControllerService":false,"sensitive":false},"schema-name":{"name":"schema-name","displayName":"Schema Name","identifiesControllerService":false,"sensitive":false},"cache-size":{"name":"cache-size","displayName":"Cache Size","identifiesControllerService":false,"sensitive":false},"schema-registry":{"name":"schema-registry","displayName":"Schema Registry","identifiesControllerService":true,"sensitive":false},"schema-access-strategy":{"name":"schema-access-strategy","displayName":"Schema Access Strategy","identifiesControllerService":false,"sensitive":false},"schema-protocol-version":{"name":"schema-protocol-version","displayName":"Schema Protocol Version","identifiesControllerService":false,"sensitive":false},"schema-version":{"name":"schema-version","displayName":"Schema Version","identifiesControllerService":false,"sensitive":false},"encoder-pool-size":{"name":"encoder-pool-size","displayName":"Encoder Pool Size","identifiesControllerService":false,"sensitive":false},"schema-cache":{"name":"schema-cache","displayName":"Schema Cache","identifiesControllerService":true,"sensitive":false},"schema-text":{"name":"schema-text","displayName":"Schema Text","identifiesControllerService":false,"sensitive":false}},"controllerServiceApis":[{"type":"org.apache.nifi.serialization.RecordSetWriterFactory","bundle":{"group":"org.apache.nifi","artifact":"nifi-standard-services-api-nar","version":"1.23.1.2.1.6.0-323"}}],"scheduledState":"DISABLED","bulletinLevel":"WARN","componentType":"CONTROLLER_SERVICE","groupIdentifier":"88c21c99-eba0-3bb8-800f-cba645bb9cb7"},{"identifier":"48efdb85-9a78-3d93-8d5f-5ff3e823f9cb","instanceIdentifier":"5f1dd039-129a-3769-9f88-6f9eda48f95e","name":"HortonworksSchemaRegistry","comments":"","type":"org.apache.nifi.schemaregistry.hortonworks.HortonworksSchemaRegistry","bundle":{"group":"org.apache.nifi","artifact":"nifi-hwx-schema-registry-nar","version":"1.23.1.2.1.6.0-323"},"properties":{"cache-expiration":"3 minutes","kerberos-credentials-service":null,"ssl-context-service":null,"cache-size":"1000","kerberos-principal":null,"basic-auth-username":null,"url":"http://3.144.230.228:7788/api/v1"},"propertyDescriptors":{"cache-expiration":{"name":"cache-expiration","displayName":"Cache Expiration","identifiesControllerService":false,"sensitive":false},"kerberos-credentials-service":{"name":"kerberos-credentials-service","displayName":"Kerberos Credentials Service","identifiesControllerService":true,"sensitive":false},"kerberos-password":{"name":"kerberos-password","displayName":"Kerberos Password","identifiesControllerService":false,"sensitive":true},"ssl-context-service":{"name":"ssl-context-service","displayName":"SSL Context Service","identifiesControllerService":true,"sensitive":false},"cache-size":{"name":"cache-size","displayName":"Cache Size","identifiesControllerService":false,"sensitive":false},"basic-auth-password":{"name":"basic-auth-password","displayName":"Basic Authentication Password","identifiesControllerService":false,"sensitive":true},"kerberos-principal":{"name":"kerberos-principal","displayName":"Kerberos Principal","identifiesControllerService":false,"sensitive":false},"basic-auth-username":{"name":"basic-auth-username","displayName":"Basic Authentication Username","identifiesControllerService":false,"sensitive":false},"url":{"name":"url","displayName":"Schema Registry URL","identifiesControllerService":false,"sensitive":false}},"controllerServiceApis":[{"type":"org.apache.nifi.schemaregistry.services.SchemaRegistry","bundle":{"group":"org.apache.nifi","artifact":"nifi-standard-services-api-nar","version":"1.23.1.2.1.6.0-323"}}],"scheduledState":"DISABLED","bulletinLevel":"WARN","componentType":"CONTROLLER_SERVICE","groupIdentifier":"88c21c99-eba0-3bb8-800f-cba645bb9cb7"},{"identifier":"8634dc34-97ef-37d6-aeec-f9f6c43ac091","instanceIdentifier":"915e8d63-c973-3ccd-b38f-570133ef23bc","name":"HortonworksSchemaRegistry","comments":"","type":"org.apache.nifi.schemaregistry.hortonworks.HortonworksSchemaRegistry","bundle":{"group":"org.apache.nifi","artifact":"nifi-hwx-schema-registry-nar","version":"1.23.1.2.1.6.0-323"},"properties":{"cache-expiration":"3 minutes","kerberos-credentials-service":null,"ssl-context-service":null,"cache-size":"1000","kerberos-principal":null,"basic-auth-username":null,"url":"http://3.144.230.228:7788/api/v1"},"propertyDescriptors":{"cache-expiration":{"name":"cache-expiration","displayName":"Cache Expiration","identifiesControllerService":false,"sensitive":false},"kerberos-credentials-service":{"name":"kerberos-credentials-service","displayName":"Kerberos Credentials Service","identifiesControllerService":true,"sensitive":false},"kerberos-password":{"name":"kerberos-password","displayName":"Kerberos Password","identifiesControllerService":false,"sensitive":true},"ssl-context-service":{"name":"ssl-context-service","displayName":"SSL Context Service","identifiesControllerService":true,"sensitive":false},"cache-size":{"name":"cache-size","displayName":"Cache Size","identifiesControllerService":false,"sensitive":false},"basic-auth-password":{"name":"basic-auth-password","displayName":"Basic Authentication Password","identifiesControllerService":false,"sensitive":true},"kerberos-principal":{"name":"kerberos-principal","displayName":"Kerberos Principal","identifiesControllerService":false,"sensitive":false},"basic-auth-username":{"name":"basic-auth-username","displayName":"Basic Authentication Username","identifiesControllerService":false,"sensitive":false},"url":{"name":"url","displayName":"Schema Registry URL","identifiesControllerService":false,"sensitive":false}},"controllerServiceApis":[{"type":"org.apache.nifi.schemaregistry.services.SchemaRegistry","bundle":{"group":"org.apache.nifi","artifact":"nifi-standard-services-api-nar","version":"1.23.1.2.1.6.0-323"}}],"scheduledState":"DISABLED","bulletinLevel":"WARN","componentType":"CONTROLLER_SERVICE","groupIdentifier":"48c4ba6e-d338-32aa-ba8f-640cbd9fa6f4"},{"identifier":"2224fa09-7305-3d59-838d-a39f264238aa","instanceIdentifier":"9a314585-b838-3ce0-a044-c21a4d66075d","name":"Event-Json-Reader","comments":"","type":"org.apache.nifi.json.JsonTreeReader","bundle":{"group":"org.apache.nifi","artifact":"nifi-record-serialization-services-nar","version":"1.23.1.2.1.6.0-323"},"properties":{"schema-branch":null,"schema-application-strategy":"SELECTED_PART","Timestamp Format":null,"schema-inference-cache":null,"Date Format":null,"schema-name":"${schema.name}","starting-field-strategy":"ROOT_NODE","schema-registry":"48efdb85-9a78-3d93-8d5f-5ff3e823f9cb","starting-field-name":null,"Time Format":null,"schema-access-strategy":"schema-name","schema-version":null,"schema-text":"${avro.schema}"},"propertyDescriptors":{"schema-branch":{"name":"schema-branch","displayName":"Schema Branch","identifiesControllerService":false,"sensitive":false},"schema-application-strategy":{"name":"schema-application-strategy","displayName":"Schema Application Strategy","identifiesControllerService":false,"sensitive":false},"Timestamp Format":{"name":"Timestamp Format","displayName":"Timestamp Format","identifiesControllerService":false,"sensitive":false},"schema-inference-cache":{"name":"schema-inference-cache","displayName":"Schema Inference Cache","identifiesControllerService":true,"sensitive":false},"Date Format":{"name":"Date Format","displayName":"Date Format","identifiesControllerService":false,"sensitive":false},"schema-name":{"name":"schema-name","displayName":"Schema Name","identifiesControllerService":false,"sensitive":false},"starting-field-strategy":{"name":"starting-field-strategy","displayName":"Starting Field Strategy","identifiesControllerService":false,"sensitive":false},"schema-registry":{"name":"schema-registry","displayName":"Schema Registry","identifiesControllerService":true,"sensitive":false},"starting-field-name":{"name":"starting-field-name","displayName":"Starting Field Name","identifiesControllerService":false,"sensitive":false},"Time Format":{"name":"Time Format","displayName":"Time Format","identifiesControllerService":false,"sensitive":false},"schema-access-strategy":{"name":"schema-access-strategy","displayName":"Schema Access Strategy","identifiesControllerService":false,"sensitive":false},"schema-version":{"name":"schema-version","displayName":"Schema Version","identifiesControllerService":false,"sensitive":false},"schema-text":{"name":"schema-text","displayName":"Schema Text","identifiesControllerService":false,"sensitive":false}},"controllerServiceApis":[{"type":"org.apache.nifi.serialization.RecordReaderFactory","bundle":{"group":"org.apache.nifi","artifact":"nifi-standard-services-api-nar","version":"1.23.1.2.1.6.0-323"}}],"scheduledState":"DISABLED","bulletinLevel":"WARN","componentType":"CONTROLLER_SERVICE","groupIdentifier":"88c21c99-eba0-3bb8-800f-cba645bb9cb7"}],"variables":{},"defaultFlowFileExpiration":"0 sec","defaultBackPressureObjectThreshold":10000,"defaultBackPressureDataSizeThreshold":"1 GB","componentType":"PROCESS_GROUP","flowFileConcurrency":"UNBOUNDED","flowFileOutboundPolicy":"STREAM_WHEN_AVAILABLE"},"externalControllerServices":{},"parameterContexts":{},"flowEncodingVersion":"1.0","parameterProviders":{},"latest":false}